{"1d6c339a-7d6a-48ef-875a-947f64b35ee9":{"name":"Field 6 AN_Independence 22x18","date":"2025-01-30","actual_crop_production":8.7,"actual_evapotranspiration":0.3,"actual_evapotranspiration_applied_water":0.11,"actual_evapotranspiration_applied_water_cumulative":1050.01,"actual_evapotranspiration_cumulative":1821.05,"actual_transpiration":0.1,"actual_transpiration_cumulative":953.8,"adviced_applied_water":8.5,"air_temperature_24":9.1,"applied_water_avg_10d":1.08,"applied_water_fcdp0":8.456,"applied_water_fcdp1":0,"applied_water_fcdp2":0,"applied_water_fcdp3":0,"applied_water_fcdp4":0,"applied_water_fcdp5":0,"applied_water_fcdp6":0,"applied_water_fcdp7":0,"area_percentage_over_irrigation":0,"area_percentage_requiring_irrigation":100,"attainable_crop_production":8.656,"critical_soil_moisture_root_zone":0.119,"crop_production_cumulative":58594,"crop_production_percentile5":8.656,"crop_production_percentile95":8.656,"et_fcdp0":0.458,"et_fcdp1":0.306,"et_fcdp2":0.342,"et_fcdp3":0.998,"et_fcdp4":0.721,"et_fcdp5":0.712,"et_fcdp6":0.719,"et_fcdp7":0.727,"field_efficiency_avg_10d":85,"forecast_et0_8days_sum":9.1,"fullness":11,"irrigation_amount_cumulative":1536.36,"irrigation_yesno":1,"leaf_nitrogen":1.037,"leaf_water_potential":-20.029,"ls_day":0,"moisture_content_cane":66.16,"net_carbon_supply_in_soil":1.1365,"ndvi":0.31,"organic_matter":1.831,"penmann_monteith_crop_coefficient_kc_avg_10d":0.73,"penmann_monteith_reference_et0":1,"potential_transpiration":0.1,"precipitation_avg_10d":1.69,"precipitation_cumulative":913.89,"precipitation_fcdp0":2.8,"precipitation_fcdp1":39.7,"precipitation_fcdp2":3.2,"precipitation_fcdp3":0,"precipitation_fcdp4":23,"precipitation_fcdp5":0,"precipitation_fcdp6":0.5,"precipitation_fcdp7":0.25,"production_gap":0,"quality_per":100,"relative_humidity_24":79.1,"root_depth":977,"s2_day":1,"soil_moisture_holding_capacity":137,"soil_moisture_percentile5":0.122,"soil_moisture_percentile95":0.122,"soil_moisture_root_zone":0.122,"soil_moisture_root_zone_irri_fcdp0":0.138,"soil_moisture_root_zone_irri_fcdp1":0.157,"soil_moisture_root_zone_irri_fcdp2":0.159,"soil_moisture_root_zone_irri_fcdp3":0.158,"soil_moisture_root_zone_irri_fcdp4":0.171,"soil_moisture_root_zone_irri_fcdp5":0.171,"soil_moisture_root_zone_irri_fcdp6":0.17,"soil_moisture_root_zone_irri_fcdp7":0.17,"soil_moisture_root_zone_no_irri_fcdp0":0.124,"soil_moisture_root_zone_no_irri_fcdp1":0.144,"soil_moisture_root_zone_no_irri_fcdp2":0.146,"soil_moisture_root_zone_no_irri_fcdp3":0.145,"soil_moisture_root_zone_no_irri_fcdp4":0.158,"soil_moisture_root_zone_no_irri_fcdp5":0.157,"soil_moisture_root_zone_no_irri_fcdp6":0.157,"soil_moisture_root_zone_no_irri_fcdp7":0.156,"soil_temperature":12.185,"soil_water_potential_critical":-1000,"soil_water_potential_fc":-100,"soil_water_potential_percentile5":-808.131,"soil_water_potential_percentile95":-808.131,"soil_water_potential_root_zone":-808.1,"solar_radiation_cumulative":178583.7,"stomatal_conductance":2.37,"sugar_content_cane":16.351,"thermal_degrees_days_cumulative":9633.893,"thermal_update":1,"theta_fc_sub":0.243,"theta_sat_sub":0.428,"theta_wp_sub":0.106,"time_until_next_irrigation":0,"uniformity_soil_moisture":0,"uniformity_vegetation_cover_stdmean":0,"utc_ls_datetime":"2025-01-28 18:40","utc_s2_datetime":"2025-01-30 18:45","vegetation_cover":30.4,"vegetation_cover_percentile5":30.4,"vegetation_cover_percentile95":30.4,"visible_update":0,"water_productivity_avg_10d":1.67,"water_unlimited_crop_production":8.7},"c49f3199-1a88-4895-ae82-460204d31d73":{"name":"Field 6 A_Independence 22x9","date":"2025-01-30","actual_crop_production":14.7,"actual_evapotranspiration":0.3,"actual_evapotranspiration_applied_water":0.1,"actual_evapotranspiration_applied_water_cumulative":1104.72,"actual_evapotranspiration_cumulative":1841.16,"actual_transpiration":0.1,"actual_transpiration_cumulative":966.2,"adviced_applied_water":10.1,"air_temperature_24":9.1,"applied_water_avg_10d":1.24,"applied_water_fcdp0":10.123,"applied_water_fcdp1":0,"applied_water_fcdp2":0,"applied_water_fcdp3":0,"applied_water_fcdp4":0,"applied_water_fcdp5":0,"applied_water_fcdp6":0,"applied_water_fcdp7":0,"area_percentage_over_irrigation":0,"area_percentage_requiring_irrigation":100,"attainable_crop_production":17.774,"critical_soil_moisture_root_zone":0.121,"crop_production_cumulative":55075,"crop_production_percentile5":8.438,"crop_production_percentile95":18.338,"et_fcdp0":0.441,"et_fcdp1":0.294,"et_fcdp2":0.328,"et_fcdp3":0.956,"et_fcdp4":0.68,"et_fcdp5":0.69,"et_fcdp6":0.694,"et_fcdp7":0.701,"field_efficiency_avg_10d":84,"forecast_et0_8days_sum":9.47,"fullness":14,"irrigation_amount_cumulative":1570.7,"irrigation_yesno":1,"leaf_nitrogen":1.109,"leaf_water_potential":-18.544,"ls_day":0,"moisture_content_cane":66.566,"net_carbon_supply_in_soil":1.2683,"ndvi":0.39,"organic_matter":1.817,"penmann_monteith_crop_coefficient_kc_avg_10d":0.75,"penmann_monteith_reference_et0":1,"potential_transpiration":0.2,"precipitation_avg_10d":1.69,"precipitation_cumulative":913.89,"precipitation_fcdp0":2.8,"precipitation_fcdp1":39.7,"precipitation_fcdp2":3.2,"precipitation_fcdp3":0,"precipitation_fcdp4":23,"precipitation_fcdp5":0,"precipitation_fcdp6":0.5,"precipitation_fcdp7":0.25,"production_gap":3.091,"quality_per":100,"relative_humidity_24":79.1,"root_depth":958,"s2_day":1,"soil_moisture_holding_capacity":139,"soil_moisture_percentile5":0.125,"soil_moisture_percentile95":0.129,"soil_moisture_root_zone":0.127,"soil_moisture_root_zone_irri_fcdp0":0.144,"soil_moisture_root_zone_irri_fcdp1":0.167,"soil_moisture_root_zone_irri_fcdp2":0.169,"soil_moisture_root_zone_irri_fcdp3":0.168,"soil_moisture_root_zone_irri_fcdp4":0.183,"soil_moisture_root_zone_irri_fcdp5":0.183,"soil_moisture_root_zone_irri_fcdp6":0.182,"soil_moisture_root_zone_irri_fcdp7":0.182,"soil_moisture_root_zone_no_irri_fcdp0":0.129,"soil_moisture_root_zone_no_irri_fcdp1":0.153,"soil_moisture_root_zone_no_irri_fcdp2":0.155,"soil_moisture_root_zone_no_irri_fcdp3":0.154,"soil_moisture_root_zone_no_irri_fcdp4":0.17,"soil_moisture_root_zone_no_irri_fcdp5":0.169,"soil_moisture_root_zone_no_irri_fcdp6":0.169,"soil_moisture_root_zone_no_irri_fcdp7":0.168,"soil_temperature":12.501,"soil_water_potential_critical":-1000,"soil_water_potential_fc":-100,"soil_water_potential_percentile5":-767.209,"soil_water_potential_percentile95":-659.388,"soil_water_potential_root_zone":-701.5,"solar_radiation_cumulative":178603.1,"stomatal_conductance":2.67,"sugar_content_cane":16.025,"thermal_degrees_days_cumulative":9629.394,"thermal_update":1,"theta_fc_sub":0.246,"theta_sat_sub":0.429,"theta_wp_sub":0.107,"time_until_next_irrigation":0,"uniformity_soil_moisture":0.016,"uniformity_vegetation_cover_stdmean":0.147,"utc_ls_datetime":"2025-01-28 18:40","utc_s2_datetime":"2025-01-30 18:45","vegetation_cover":42.3,"vegetation_cover_percentile5":30,"vegetation_cover_percentile95":49.4,"visible_update":0,"water_productivity_avg_10d":2.68,"water_unlimited_crop_production":14.7},"c715d69c-8aa3-44a1-9c1f-8c88810fd362":{"name":"Field 3N_22x18 Butte and padre","date":"2025-01-30","actual_crop_production":12,"actual_evapotranspiration":0.3,"actual_evapotranspiration_applied_water":0.12,"actual_evapotranspiration_applied_water_cumulative":1358.8,"actual_evapotranspiration_cumulative":2214.62,"actual_transpiration":0.1,"actual_transpiration_cumulative":1305.4,"adviced_applied_water":9.4,"air_temperature_24":9.1,"applied_water_avg_10d":1.5,"applied_water_fcdp0":9.385,"applied_water_fcdp1":0,"applied_water_fcdp2":0,"applied_water_fcdp3":0,"applied_water_fcdp4":0,"applied_water_fcdp5":0,"applied_water_fcdp6":0,"applied_water_fcdp7":0,"area_percentage_over_irrigation":0,"area_percentage_requiring_irrigation":100,"attainable_crop_production":14.543,"critical_soil_moisture_root_zone":0.117,"crop_production_cumulative":86070,"crop_production_percentile5":8.934,"crop_production_percentile95":14.978,"et_fcdp0":0.452,"et_fcdp1":0.302,"et_fcdp2":0.337,"et_fcdp3":0.985,"et_fcdp4":0.713,"et_fcdp5":0.702,"et_fcdp6":0.71,"et_fcdp7":0.717,"field_efficiency_avg_10d":84,"forecast_et0_8days_sum":9.07,"fullness":12,"irrigation_amount_cumulative":1952.45,"irrigation_yesno":1,"leaf_nitrogen":1.076,"leaf_water_potential":-18.064,"ls_day":0,"moisture_content_cane":66.378,"net_carbon_supply_in_soil":1.1798,"ndvi":0.36,"organic_matter":1.814,"penmann_monteith_crop_coefficient_kc_avg_10d":0.72,"penmann_monteith_reference_et0":1,"potential_transpiration":0.2,"precipitation_avg_10d":1.69,"precipitation_cumulative":913.89,"precipitation_fcdp0":2.8,"precipitation_fcdp1":39.7,"precipitation_fcdp2":3.2,"precipitation_fcdp3":0,"precipitation_fcdp4":23,"precipitation_fcdp5":0,"precipitation_fcdp6":0.5,"precipitation_fcdp7":0.25,"production_gap":2.578,"quality_per":100,"relative_humidity_24":79.1,"root_depth":1052,"s2_day":1,"soil_moisture_holding_capacity":136,"soil_moisture_percentile5":0.121,"soil_moisture_percentile95":0.124,"soil_moisture_root_zone":0.122,"soil_moisture_root_zone_irri_fcdp0":0.137,"soil_moisture_root_zone_irri_fcdp1":0.157,"soil_moisture_root_zone_irri_fcdp2":0.159,"soil_moisture_root_zone_irri_fcdp3":0.158,"soil_moisture_root_zone_irri_fcdp4":0.171,"soil_moisture_root_zone_irri_fcdp5":0.171,"soil_moisture_root_zone_irri_fcdp6":0.17,"soil_moisture_root_zone_irri_fcdp7":0.17,"soil_moisture_root_zone_no_irri_fcdp0":0.124,"soil_moisture_root_zone_no_irri_fcdp1":0.144,"soil_moisture_root_zone_no_irri_fcdp2":0.146,"soil_moisture_root_zone_no_irri_fcdp3":0.145,"soil_moisture_root_zone_no_irri_fcdp4":0.159,"soil_moisture_root_zone_no_irri_fcdp5":0.158,"soil_moisture_root_zone_no_irri_fcdp6":0.158,"soil_moisture_root_zone_no_irri_fcdp7":0.157,"soil_temperature":13.064,"soil_water_potential_critical":-1000,"soil_water_potential_fc":-100,"soil_water_potential_percentile5":-805.193,"soil_water_potential_percentile95":-693.347,"soil_water_potential_root_zone":-746.9,"solar_radiation_cumulative":178576.4,"stomatal_conductance":2.59,"sugar_content_cane":16.176,"thermal_degrees_days_cumulative":9633.891,"thermal_update":1,"theta_fc_sub":0.241,"theta_sat_sub":0.427,"theta_wp_sub":0.105,"time_until_next_irrigation":0,"uniformity_soil_moisture":0.008,"uniformity_vegetation_cover_stdmean":0.103,"utc_ls_datetime":"2025-01-28 18:40","utc_s2_datetime":"2025-01-30 18:45","vegetation_cover":37,"vegetation_cover_percentile5":31.1,"vegetation_cover_percentile95":43,"visible_update":0,"water_productivity_avg_10d":2.13,"water_unlimited_crop_production":12},"8f95e554-5a9b-4fe5-a046-947e978e3867":{"name":"Field 1_Walnuts Tulare","date":"2025-01-30","actual_crop_production":9.3,"actual_evapotranspiration":0.2,"actual_evapotranspiration_applied_water":0.04,"actual_evapotranspiration_applied_water_cumulative":592.02,"actual_evapotranspiration_cumulative":1123,"actual_transpiration":0.1,"actual_transpiration_cumulative":469.7,"adviced_applied_water":8.5,"air_temperature_24":9.1,"applied_water_avg_10d":0.81,"applied_water_fcdp0":8.463,"applied_water_fcdp1":0,"applied_water_fcdp2":0,"applied_water_fcdp3":0,"applied_water_fcdp4":0,"applied_water_fcdp5":0,"applied_water_fcdp6":0,"applied_water_fcdp7":0,"area_percentage_over_irrigation":0,"area_percentage_requiring_irrigation":100,"attainable_crop_production":18.408,"critical_soil_moisture_root_zone":0.114,"crop_production_cumulative":18374,"crop_production_percentile5":3.279,"crop_production_percentile95":14.935,"et_fcdp0":0.324,"et_fcdp1":0.216,"et_fcdp2":0.241,"et_fcdp3":0.704,"et_fcdp4":0.507,"et_fcdp5":0.504,"et_fcdp6":0.509,"et_fcdp7":0.514,"field_efficiency_avg_10d":84,"forecast_et0_8days_sum":9.19,"fullness":8,"irrigation_amount_cumulative":866.19,"irrigation_yesno":1,"leaf_nitrogen":1.081,"leaf_water_potential":-13.765,"ls_day":0,"moisture_content_cane":66.6,"net_carbon_supply_in_soil":1.3169,"ndvi":0.35,"organic_matter":1.522,"penmann_monteith_crop_coefficient_kc_avg_10d":0.51,"penmann_monteith_reference_et0":1,"potential_transpiration":0.1,"precipitation_avg_10d":1.69,"precipitation_cumulative":913.89,"precipitation_fcdp0":2.8,"precipitation_fcdp1":39.7,"precipitation_fcdp2":3.2,"precipitation_fcdp3":0,"precipitation_fcdp4":23,"precipitation_fcdp5":0,"precipitation_fcdp6":0.5,"precipitation_fcdp7":0.25,"production_gap":9.071,"quality_per":100,"relative_humidity_24":79.1,"root_depth":790,"s2_day":1,"soil_moisture_holding_capacity":132,"soil_moisture_percentile5":0.11,"soil_moisture_percentile95":0.114,"soil_moisture_root_zone":0.112,"soil_moisture_root_zone_irri_fcdp0":0.132,"soil_moisture_root_zone_irri_fcdp1":0.158,"soil_moisture_root_zone_irri_fcdp2":0.161,"soil_moisture_root_zone_irri_fcdp3":0.16,"soil_moisture_root_zone_irri_fcdp4":0.177,"soil_moisture_root_zone_irri_fcdp5":0.177,"soil_moisture_root_zone_irri_fcdp6":0.176,"soil_moisture_root_zone_irri_fcdp7":0.176,"soil_moisture_root_zone_no_irri_fcdp0":0.115,"soil_moisture_root_zone_no_irri_fcdp1":0.141,"soil_moisture_root_zone_no_irri_fcdp2":0.144,"soil_moisture_root_zone_no_irri_fcdp3":0.143,"soil_moisture_root_zone_no_irri_fcdp4":0.161,"soil_moisture_root_zone_no_irri_fcdp5":0.161,"soil_moisture_root_zone_no_irri_fcdp6":0.16,"soil_moisture_root_zone_no_irri_fcdp7":0.16,"soil_temperature":12.906,"soil_water_potential_critical":-750,"soil_water_potential_fc":-100,"soil_water_potential_percentile5":-993.3,"soil_water_potential_percentile95":-759.118,"soil_water_potential_root_zone":-860.3,"solar_radiation_cumulative":178582.5,"stomatal_conductance":2.24,"sugar_content_cane":15.998,"thermal_degrees_days_cumulative":7616.976,"thermal_update":1,"theta_fc_sub":0.231,"theta_sat_sub":0.423,"theta_wp_sub":0.099,"time_until_next_irrigation":0,"uniformity_soil_moisture":0.009,"uniformity_vegetation_cover_stdmean":0.26,"utc_ls_datetime":"2025-01-28 18:40","utc_s2_datetime":"2025-01-30 18:45","vegetation_cover":30.4,"vegetation_cover_percentile5":16,"vegetation_cover_percentile95":41.6,"visible_update":0,"water_productivity_avg_10d":2.39,"water_unlimited_crop_production":14.3},"cd78e96c-d5cf-4982-af33-36bd15090453":{"name":"Field 6 A_22x9 Independence","date":"2025-01-30","actual_crop_production":5.3,"actual_evapotranspiration":0.3,"actual_evapotranspiration_applied_water":0.11,"actual_evapotranspiration_applied_water_cumulative":811.35,"actual_evapotranspiration_cumulative":1384.71,"actual_transpiration":0.1,"actual_transpiration_cumulative":665.6,"adviced_applied_water":7.2,"air_temperature_24":9.1,"applied_water_avg_10d":0.91,"applied_water_fcdp0":7.242,"applied_water_fcdp1":0,"applied_water_fcdp2":0,"applied_water_fcdp3":0,"applied_water_fcdp4":0,"applied_water_fcdp5":0,"applied_water_fcdp6":0,"applied_water_fcdp7":0,"area_percentage_over_irrigation":0,"area_percentage_requiring_irrigation":100,"attainable_crop_production":6.3,"critical_soil_moisture_root_zone":0.118,"crop_production_cumulative":32302,"crop_production_percentile5":4.007,"crop_production_percentile95":6.288,"et_fcdp0":0.389,"et_fcdp1":0.26,"et_fcdp2":0.29,"et_fcdp3":0.845,"et_fcdp4":0.607,"et_fcdp5":0.606,"et_fcdp6":0.611,"et_fcdp7":0.617,"field_efficiency_avg_10d":82,"forecast_et0_8days_sum":9.23,"fullness":9,"irrigation_amount_cumulative":1137.65,"irrigation_yesno":1,"leaf_nitrogen":0.972,"leaf_water_potential":-23.237,"ls_day":0,"moisture_content_cane":66.138,"net_carbon_supply_in_soil":1.1441,"ndvi":0.25,"organic_matter":1.461,"penmann_monteith_crop_coefficient_kc_avg_10d":0.6,"penmann_monteith_reference_et0":1,"potential_transpiration":0.1,"precipitation_avg_10d":1.69,"precipitation_cumulative":913.89,"precipitation_fcdp0":2.8,"precipitation_fcdp1":39.7,"precipitation_fcdp2":3.2,"precipitation_fcdp3":0,"precipitation_fcdp4":23,"precipitation_fcdp5":0,"precipitation_fcdp6":0.5,"precipitation_fcdp7":0.25,"production_gap":0.974,"quality_per":100,"relative_humidity_24":79.1,"root_depth":922,"s2_day":1,"soil_moisture_holding_capacity":137,"soil_moisture_percentile5":0.119,"soil_moisture_percentile95":0.122,"soil_moisture_root_zone":0.121,"soil_moisture_root_zone_irri_fcdp0":0.138,"soil_moisture_root_zone_irri_fcdp1":0.156,"soil_moisture_root_zone_irri_fcdp2":0.159,"soil_moisture_root_zone_irri_fcdp3":0.158,"soil_moisture_root_zone_irri_fcdp4":0.171,"soil_moisture_root_zone_irri_fcdp5":0.17,"soil_moisture_root_zone_irri_fcdp6":0.17,"soil_moisture_root_zone_irri_fcdp7":0.169,"soil_moisture_root_zone_no_irri_fcdp0":0.123,"soil_moisture_root_zone_no_irri_fcdp1":0.142,"soil_moisture_root_zone_no_irri_fcdp2":0.144,"soil_moisture_root_zone_no_irri_fcdp3":0.143,"soil_moisture_root_zone_no_irri_fcdp4":0.157,"soil_moisture_root_zone_no_irri_fcdp5":0.156,"soil_moisture_root_zone_no_irri_fcdp6":0.156,"soil_moisture_root_zone_no_irri_fcdp7":0.155,"soil_temperature":12.402,"soil_water_potential_critical":-1000,"soil_water_potential_fc":-100,"soil_water_potential_percentile5":-892.536,"soil_water_potential_percentile95":-752.659,"soil_water_potential_root_zone":-817.4,"solar_radiation_cumulative":178590.2,"stomatal_conductance":1.97,"sugar_content_cane":16.369,"thermal_degrees_days_cumulative":9629.393,"thermal_update":1,"theta_fc_sub":0.242,"theta_sat_sub":0.427,"theta_wp_sub":0.105,"time_until_next_irrigation":0,"uniformity_soil_moisture":0.008,"uniformity_vegetation_cover_stdmean":0.101,"utc_ls_datetime":"2025-01-28 18:40","utc_s2_datetime":"2025-01-30 18:45","vegetation_cover":21.7,"vegetation_cover_percentile5":18.1,"vegetation_cover_percentile95":24.2,"visible_update":0,"water_productivity_avg_10d":1.09,"water_unlimited_crop_production":5.5},"b77e3506-6854-4ecc-8758-8bc465f83b15":{"name":"Field 6 BS_22x18 Non pareil and Fritz","date":"2025-01-30","actual_crop_production":25.1,"actual_evapotranspiration":0.3,"actual_evapotranspiration_applied_water":0.1,"actual_evapotranspiration_applied_water_cumulative":1467.33,"actual_evapotranspiration_cumulative":2497.48,"actual_transpiration":0.1,"actual_transpiration_cumulative":1611.6,"adviced_applied_water":8.5,"air_temperature_24":9.1,"applied_water_avg_10d":1.34,"applied_water_fcdp0":8.469,"applied_water_fcdp1":0,"applied_water_fcdp2":0,"applied_water_fcdp3":0,"applied_water_fcdp4":0,"applied_water_fcdp5":0,"applied_water_fcdp6":0,"applied_water_fcdp7":0,"area_percentage_over_irrigation":0,"area_percentage_requiring_irrigation":63,"attainable_crop_production":29.081,"critical_soil_moisture_root_zone":0.116,"crop_production_cumulative":105777,"crop_production_percentile5":20.216,"crop_production_percentile95":30.23,"et_fcdp0":0.45,"et_fcdp1":0.301,"et_fcdp2":0.335,"et_fcdp3":0.977,"et_fcdp4":0.697,"et_fcdp5":0.704,"et_fcdp6":0.708,"et_fcdp7":0.715,"field_efficiency_avg_10d":85,"forecast_et0_8days_sum":9.38,"fullness":16,"irrigation_amount_cumulative":2121.48,"irrigation_yesno":1,"leaf_nitrogen":1.322,"leaf_water_potential":-16.917,"ls_day":0,"moisture_content_cane":67.831,"net_carbon_supply_in_soil":1.4808,"ndvi":0.51,"organic_matter":1.85,"penmann_monteith_crop_coefficient_kc_avg_10d":0.76,"penmann_monteith_reference_et0":1,"potential_transpiration":0.3,"precipitation_avg_10d":1.69,"precipitation_cumulative":913.89,"precipitation_fcdp0":2.8,"precipitation_fcdp1":39.7,"precipitation_fcdp2":3.2,"precipitation_fcdp3":0,"precipitation_fcdp4":23,"precipitation_fcdp5":0,"precipitation_fcdp6":0.5,"precipitation_fcdp7":0.25,"production_gap":4.025,"quality_per":100,"relative_humidity_24":79.1,"root_depth":1076,"s2_day":1,"soil_moisture_holding_capacity":135,"soil_moisture_percentile5":0.123,"soil_moisture_percentile95":0.129,"soil_moisture_root_zone":0.126,"soil_moisture_root_zone_irri_fcdp0":0.136,"soil_moisture_root_zone_irri_fcdp1":0.161,"soil_moisture_root_zone_irri_fcdp2":0.163,"soil_moisture_root_zone_irri_fcdp3":0.162,"soil_moisture_root_zone_irri_fcdp4":0.177,"soil_moisture_root_zone_irri_fcdp5":0.176,"soil_moisture_root_zone_irri_fcdp6":0.176,"soil_moisture_root_zone_irri_fcdp7":0.176,"soil_moisture_root_zone_no_irri_fcdp0":0.128,"soil_moisture_root_zone_no_irri_fcdp1":0.152,"soil_moisture_root_zone_no_irri_fcdp2":0.154,"soil_moisture_root_zone_no_irri_fcdp3":0.153,"soil_moisture_root_zone_no_irri_fcdp4":0.169,"soil_moisture_root_zone_no_irri_fcdp5":0.168,"soil_moisture_root_zone_no_irri_fcdp6":0.168,"soil_moisture_root_zone_no_irri_fcdp7":0.167,"soil_temperature":12.717,"soil_water_potential_critical":-1000,"soil_water_potential_fc":-100,"soil_water_potential_percentile5":-641.659,"soil_water_potential_percentile95":-512.404,"soil_water_potential_root_zone":-575.9,"solar_radiation_cumulative":178596,"stomatal_conductance":3.07,"sugar_content_cane":15.011,"thermal_degrees_days_cumulative":9633.892,"thermal_update":1,"theta_fc_sub":0.239,"theta_sat_sub":0.426,"theta_wp_sub":0.104,"time_until_next_irrigation":0,"uniformity_soil_moisture":0.016,"uniformity_vegetation_cover_stdmean":0.075,"utc_ls_datetime":"2025-01-28 18:40","utc_s2_datetime":"2025-01-30 18:45","vegetation_cover":60.2,"vegetation_cover_percentile5":52.8,"vegetation_cover_percentile95":67.8,"visible_update":0,"water_productivity_avg_10d":3.84,"water_unlimited_crop_production":25.1},"32120f7a-8441-458a-9275-8c94fdad2faf":{"name":"Field 3S_22x18 Butte and padre","date":"2025-01-30","actual_crop_production":11.6,"actual_evapotranspiration":0.3,"actual_evapotranspiration_applied_water":0.14,"actual_evapotranspiration_applied_water_cumulative":1349.37,"actual_evapotranspiration_cumulative":2159.52,"actual_transpiration":0.1,"actual_transpiration_cumulative":1299.8,"adviced_applied_water":9.3,"air_temperature_24":9.1,"applied_water_avg_10d":1.52,"applied_water_fcdp0":9.298,"applied_water_fcdp1":0,"applied_water_fcdp2":0,"applied_water_fcdp3":0,"applied_water_fcdp4":0,"applied_water_fcdp5":0,"applied_water_fcdp6":0,"applied_water_fcdp7":0,"area_percentage_over_irrigation":0,"area_percentage_requiring_irrigation":100,"attainable_crop_production":14.497,"critical_soil_moisture_root_zone":0.128,"crop_production_cumulative":90912,"crop_production_percentile5":7.371,"crop_production_percentile95":15.018,"et_fcdp0":0.48,"et_fcdp1":0.321,"et_fcdp2":0.358,"et_fcdp3":1.042,"et_fcdp4":0.746,"et_fcdp5":0.75,"et_fcdp6":0.755,"et_fcdp7":0.762,"field_efficiency_avg_10d":85,"forecast_et0_8days_sum":9.33,"fullness":14,"irrigation_amount_cumulative":1922.72,"irrigation_yesno":1,"leaf_nitrogen":1.096,"leaf_water_potential":-16.024,"ls_day":0,"moisture_content_cane":66.448,"net_carbon_supply_in_soil":0.8795,"ndvi":0.35,"organic_matter":2.806,"penmann_monteith_crop_coefficient_kc_avg_10d":0.68,"penmann_monteith_reference_et0":1,"potential_transpiration":0.2,"precipitation_avg_10d":1.69,"precipitation_cumulative":913.89,"precipitation_fcdp0":2.8,"precipitation_fcdp1":39.7,"precipitation_fcdp2":3.2,"precipitation_fcdp3":0,"precipitation_fcdp4":23,"precipitation_fcdp5":0,"precipitation_fcdp6":0.5,"precipitation_fcdp7":0.25,"production_gap":2.924,"quality_per":100,"relative_humidity_24":79.1,"root_depth":1064,"s2_day":1,"soil_moisture_holding_capacity":142,"soil_moisture_percentile5":0.13,"soil_moisture_percentile95":0.134,"soil_moisture_root_zone":0.132,"soil_moisture_root_zone_irri_fcdp0":0.147,"soil_moisture_root_zone_irri_fcdp1":0.166,"soil_moisture_root_zone_irri_fcdp2":0.168,"soil_moisture_root_zone_irri_fcdp3":0.167,"soil_moisture_root_zone_irri_fcdp4":0.18,"soil_moisture_root_zone_irri_fcdp5":0.179,"soil_moisture_root_zone_irri_fcdp6":0.179,"soil_moisture_root_zone_irri_fcdp7":0.179,"soil_moisture_root_zone_no_irri_fcdp0":0.134,"soil_moisture_root_zone_no_irri_fcdp1":0.154,"soil_moisture_root_zone_no_irri_fcdp2":0.156,"soil_moisture_root_zone_no_irri_fcdp3":0.155,"soil_moisture_root_zone_no_irri_fcdp4":0.168,"soil_moisture_root_zone_no_irri_fcdp5":0.167,"soil_moisture_root_zone_no_irri_fcdp6":0.167,"soil_moisture_root_zone_no_irri_fcdp7":0.166,"soil_temperature":13.263,"soil_water_potential_critical":-1000,"soil_water_potential_fc":-100,"soil_water_potential_percentile5":-880.344,"soil_water_potential_percentile95":-696.084,"soil_water_potential_root_zone":-773.8,"solar_radiation_cumulative":178590.9,"stomatal_conductance":2.49,"sugar_content_cane":16.12,"thermal_degrees_days_cumulative":9633.891,"thermal_update":1,"theta_fc_sub":0.254,"theta_sat_sub":0.433,"theta_wp_sub":0.112,"time_until_next_irrigation":0,"uniformity_soil_moisture":0.015,"uniformity_vegetation_cover_stdmean":0.137,"utc_ls_datetime":"2025-01-28 18:40","utc_s2_datetime":"2025-01-30 18:45","vegetation_cover":36.4,"vegetation_cover_percentile5":26.4,"vegetation_cover_percentile95":43.2,"visible_update":0,"water_productivity_avg_10d":2.16,"water_unlimited_crop_production":11.6},"20303241-c281-4861-90c7-e69c32ad0e49":{"name":"Field 6 AS_Independence 22x18","date":"2025-01-30","actual_crop_production":17.5,"actual_evapotranspiration":0.3,"actual_evapotranspiration_applied_water":0.09,"actual_evapotranspiration_applied_water_cumulative":1124.84,"actual_evapotranspiration_cumulative":1999.99,"actual_transpiration":0.1,"actual_transpiration_cumulative":1191.3,"adviced_applied_water":10.8,"air_temperature_24":9.1,"applied_water_avg_10d":1.19,"applied_water_fcdp0":10.838,"applied_water_fcdp1":0,"applied_water_fcdp2":0,"applied_water_fcdp3":0,"applied_water_fcdp4":0,"applied_water_fcdp5":0,"applied_water_fcdp6":0,"applied_water_fcdp7":0,"area_percentage_over_irrigation":0,"area_percentage_requiring_irrigation":100,"attainable_crop_production":21.016,"critical_soil_moisture_root_zone":0.114,"crop_production_cumulative":85684,"crop_production_percentile5":12.425,"crop_production_percentile95":21.557,"et_fcdp0":0.448,"et_fcdp1":0.299,"et_fcdp2":0.334,"et_fcdp3":0.971,"et_fcdp4":0.692,"et_fcdp5":0.701,"et_fcdp6":0.704,"et_fcdp7":0.711,"field_efficiency_avg_10d":84,"forecast_et0_8days_sum":9.41,"fullness":13,"irrigation_amount_cumulative":1643.08,"irrigation_yesno":1,"leaf_nitrogen":1.184,"leaf_water_potential":-17.824,"ls_day":0,"moisture_content_cane":67.023,"net_carbon_supply_in_soil":1.4073,"ndvi":0.43,"organic_matter":1.512,"penmann_monteith_crop_coefficient_kc_avg_10d":0.74,"penmann_monteith_reference_et0":1,"potential_transpiration":0.2,"precipitation_avg_10d":1.69,"precipitation_cumulative":913.89,"precipitation_fcdp0":2.8,"precipitation_fcdp1":39.7,"precipitation_fcdp2":3.2,"precipitation_fcdp3":0,"precipitation_fcdp4":23,"precipitation_fcdp5":0,"precipitation_fcdp6":0.5,"precipitation_fcdp7":0.25,"production_gap":3.547,"quality_per":100,"relative_humidity_24":79.1,"root_depth":1050,"s2_day":1,"soil_moisture_holding_capacity":135,"soil_moisture_percentile5":0.119,"soil_moisture_percentile95":0.123,"soil_moisture_root_zone":0.121,"soil_moisture_root_zone_irri_fcdp0":0.136,"soil_moisture_root_zone_irri_fcdp1":0.158,"soil_moisture_root_zone_irri_fcdp2":0.16,"soil_moisture_root_zone_irri_fcdp3":0.159,"soil_moisture_root_zone_irri_fcdp4":0.174,"soil_moisture_root_zone_irri_fcdp5":0.173,"soil_moisture_root_zone_irri_fcdp6":0.173,"soil_moisture_root_zone_irri_fcdp7":0.173,"soil_moisture_root_zone_no_irri_fcdp0":0.123,"soil_moisture_root_zone_no_irri_fcdp1":0.146,"soil_moisture_root_zone_no_irri_fcdp2":0.148,"soil_moisture_root_zone_no_irri_fcdp3":0.147,"soil_moisture_root_zone_no_irri_fcdp4":0.162,"soil_moisture_root_zone_no_irri_fcdp5":0.161,"soil_moisture_root_zone_no_irri_fcdp6":0.161,"soil_moisture_root_zone_no_irri_fcdp7":0.16,"soil_temperature":12.732,"soil_water_potential_critical":-1000,"soil_water_potential_fc":-100,"soil_water_potential_percentile5":-751.785,"soil_water_potential_percentile95":-601.519,"soil_water_potential_root_zone":-668.7,"solar_radiation_cumulative":178590.4,"stomatal_conductance":2.82,"sugar_content_cane":15.659,"thermal_degrees_days_cumulative":9633.891,"thermal_update":1,"theta_fc_sub":0.237,"theta_sat_sub":0.425,"theta_wp_sub":0.102,"time_until_next_irrigation":0,"uniformity_soil_moisture":0.008,"uniformity_vegetation_cover_stdmean":0.099,"utc_ls_datetime":"2025-01-28 18:40","utc_s2_datetime":"2025-01-30 18:45","vegetation_cover":47.4,"vegetation_cover_percentile5":38.3,"vegetation_cover_percentile95":54.4,"visible_update":0,"water_productivity_avg_10d":3.23,"water_unlimited_crop_production":17.5},"3e35e2a8-fde1-4360-a4e1-1e4059b89486":{"name":"Field 4_22x18 NP, Carmel, Aldrich","date":"2025-01-30","actual_crop_production":13.9,"actual_evapotranspiration":0.3,"actual_evapotranspiration_applied_water":0.14,"actual_evapotranspiration_applied_water_cumulative":1404.05,"actual_evapotranspiration_cumulative":2336.23,"actual_transpiration":0.1,"actual_transpiration_cumulative":1343.6,"adviced_applied_water":9.9,"air_temperature_24":9.1,"applied_water_avg_10d":1.29,"applied_water_fcdp0":9.87,"applied_water_fcdp1":0,"applied_water_fcdp2":0,"applied_water_fcdp3":0,"applied_water_fcdp4":0,"applied_water_fcdp5":0,"applied_water_fcdp6":0,"applied_water_fcdp7":0,"area_percentage_over_irrigation":0,"area_percentage_requiring_irrigation":99,"attainable_crop_production":17.315,"critical_soil_moisture_root_zone":0.124,"crop_production_cumulative":90238,"crop_production_percentile5":10.598,"crop_production_percentile95":18.872,"et_fcdp0":0.48,"et_fcdp1":0.321,"et_fcdp2":0.358,"et_fcdp3":1.044,"et_fcdp4":0.752,"et_fcdp5":0.748,"et_fcdp6":0.754,"et_fcdp7":0.762,"field_efficiency_avg_10d":85,"forecast_et0_8days_sum":9.19,"fullness":14,"irrigation_amount_cumulative":1981.65,"irrigation_yesno":1,"leaf_nitrogen":1.167,"leaf_water_potential":-18.827,"ls_day":0,"moisture_content_cane":66.764,"net_carbon_supply_in_soil":0.9956,"ndvi":0.39,"organic_matter":2.669,"penmann_monteith_crop_coefficient_kc_avg_10d":0.77,"penmann_monteith_reference_et0":1,"potential_transpiration":0.2,"precipitation_avg_10d":1.69,"precipitation_cumulative":913.89,"precipitation_fcdp0":2.8,"precipitation_fcdp1":39.7,"precipitation_fcdp2":3.2,"precipitation_fcdp3":0,"precipitation_fcdp4":23,"precipitation_fcdp5":0,"precipitation_fcdp6":0.5,"precipitation_fcdp7":0.25,"production_gap":3.453,"quality_per":100,"relative_humidity_24":79.1,"root_depth":1063,"s2_day":1,"soil_moisture_holding_capacity":141,"soil_moisture_percentile5":0.128,"soil_moisture_percentile95":0.132,"soil_moisture_root_zone":0.129,"soil_moisture_root_zone_irri_fcdp0":0.144,"soil_moisture_root_zone_irri_fcdp1":0.164,"soil_moisture_root_zone_irri_fcdp2":0.167,"soil_moisture_root_zone_irri_fcdp3":0.166,"soil_moisture_root_zone_irri_fcdp4":0.179,"soil_moisture_root_zone_irri_fcdp5":0.178,"soil_moisture_root_zone_irri_fcdp6":0.178,"soil_moisture_root_zone_irri_fcdp7":0.178,"soil_moisture_root_zone_no_irri_fcdp0":0.131,"soil_moisture_root_zone_no_irri_fcdp1":0.152,"soil_moisture_root_zone_no_irri_fcdp2":0.154,"soil_moisture_root_zone_no_irri_fcdp3":0.153,"soil_moisture_root_zone_no_irri_fcdp4":0.167,"soil_moisture_root_zone_no_irri_fcdp5":0.166,"soil_moisture_root_zone_no_irri_fcdp6":0.166,"soil_moisture_root_zone_no_irri_fcdp7":0.165,"soil_temperature":12.905,"soil_water_potential_critical":-1000,"soil_water_potential_fc":-100,"soil_water_potential_percentile5":-795.168,"soil_water_potential_percentile95":-653.041,"soil_water_potential_root_zone":-736.3,"solar_radiation_cumulative":178583.1,"stomatal_conductance":2.58,"sugar_content_cane":15.867,"thermal_degrees_days_cumulative":9633.892,"thermal_update":1,"theta_fc_sub":0.25,"theta_sat_sub":0.431,"theta_wp_sub":0.109,"time_until_next_irrigation":0,"uniformity_soil_moisture":0.008,"uniformity_vegetation_cover_stdmean":0.119,"utc_ls_datetime":"2025-01-28 18:40","utc_s2_datetime":"2025-01-30 18:45","vegetation_cover":41.1,"vegetation_cover_percentile5":34.7,"vegetation_cover_percentile95":50.3,"visible_update":0,"water_productivity_avg_10d":2.15,"water_unlimited_crop_production":13.9},"62aeadb5-2832-4f0b-9f9c-bd16f823989f":{"name":"Field 6 BN_22x18 Non pareil and Fritz","date":"2025-01-30","actual_crop_production":18.9,"actual_evapotranspiration":0.3,"actual_evapotranspiration_applied_water":0.1,"actual_evapotranspiration_applied_water_cumulative":1484.72,"actual_evapotranspiration_cumulative":2490.11,"actual_transpiration":0.1,"actual_transpiration_cumulative":1647.4,"adviced_applied_water":11.2,"air_temperature_24":9.1,"applied_water_avg_10d":1.26,"applied_water_fcdp0":11.193,"applied_water_fcdp1":0,"applied_water_fcdp2":0,"applied_water_fcdp3":0,"applied_water_fcdp4":0,"applied_water_fcdp5":0,"applied_water_fcdp6":0,"applied_water_fcdp7":0,"area_percentage_over_irrigation":0,"area_percentage_requiring_irrigation":100,"attainable_crop_production":23.843,"critical_soil_moisture_root_zone":0.114,"crop_production_cumulative":106229,"crop_production_percentile5":12.895,"crop_production_percentile95":24.331,"et_fcdp0":0.434,"et_fcdp1":0.29,"et_fcdp2":0.324,"et_fcdp3":0.945,"et_fcdp4":0.679,"et_fcdp5":0.677,"et_fcdp6":0.683,"et_fcdp7":0.69,"field_efficiency_avg_10d":87,"forecast_et0_8days_sum":9.22,"fullness":13,"irrigation_amount_cumulative":2149.81,"irrigation_yesno":1,"leaf_nitrogen":1.21,"leaf_water_potential":-17.895,"ls_day":0,"moisture_content_cane":67.081,"net_carbon_supply_in_soil":1.3763,"ndvi":0.44,"organic_matter":1.776,"penmann_monteith_crop_coefficient_kc_avg_10d":0.71,"penmann_monteith_reference_et0":1,"potential_transpiration":0.2,"precipitation_avg_10d":1.69,"precipitation_cumulative":913.89,"precipitation_fcdp0":2.8,"precipitation_fcdp1":39.7,"precipitation_fcdp2":3.2,"precipitation_fcdp3":0,"precipitation_fcdp4":23,"precipitation_fcdp5":0,"precipitation_fcdp6":0.5,"precipitation_fcdp7":0.25,"production_gap":4.919,"quality_per":100,"relative_humidity_24":79.1,"root_depth":1068,"s2_day":1,"soil_moisture_holding_capacity":134,"soil_moisture_percentile5":0.118,"soil_moisture_percentile95":0.123,"soil_moisture_root_zone":0.12,"soil_moisture_root_zone_irri_fcdp0":0.135,"soil_moisture_root_zone_irri_fcdp1":0.158,"soil_moisture_root_zone_irri_fcdp2":0.16,"soil_moisture_root_zone_irri_fcdp3":0.159,"soil_moisture_root_zone_irri_fcdp4":0.173,"soil_moisture_root_zone_irri_fcdp5":0.173,"soil_moisture_root_zone_irri_fcdp6":0.172,"soil_moisture_root_zone_irri_fcdp7":0.172,"soil_moisture_root_zone_no_irri_fcdp0":0.122,"soil_moisture_root_zone_no_irri_fcdp1":0.145,"soil_moisture_root_zone_no_irri_fcdp2":0.147,"soil_moisture_root_zone_no_irri_fcdp3":0.146,"soil_moisture_root_zone_no_irri_fcdp4":0.161,"soil_moisture_root_zone_no_irri_fcdp5":0.161,"soil_moisture_root_zone_no_irri_fcdp6":0.16,"soil_moisture_root_zone_no_irri_fcdp7":0.16,"soil_temperature":13.122,"soil_water_potential_critical":-1000,"soil_water_potential_fc":-100,"soil_water_potential_percentile5":-758.059,"soil_water_potential_percentile95":-583.624,"soil_water_potential_root_zone":-665,"solar_radiation_cumulative":178585.4,"stomatal_conductance":2.8,"sugar_content_cane":15.612,"thermal_degrees_days_cumulative":9633.891,"thermal_update":1,"theta_fc_sub":0.236,"theta_sat_sub":0.425,"theta_wp_sub":0.102,"time_until_next_irrigation":0,"uniformity_soil_moisture":0.017,"uniformity_vegetation_cover_stdmean":0.117,"utc_ls_datetime":"2025-01-28 18:40","utc_s2_datetime":"2025-01-30 18:45","vegetation_cover":50.3,"vegetation_cover_percentile5":39.8,"vegetation_cover_percentile95":59.1,"visible_update":0,"water_productivity_avg_10d":3.19,"water_unlimited_crop_production":18.9},"278562c1-4c05-4c92-8c95-53fdb9541b54":{"name":"Field 2_22x18 Butte and padre","date":"2025-01-30","actual_crop_production":13.8,"actual_evapotranspiration":0.3,"actual_evapotranspiration_applied_water":0.11,"actual_evapotranspiration_applied_water_cumulative":1362.14,"actual_evapotranspiration_cumulative":2230.74,"actual_transpiration":0.1,"actual_transpiration_cumulative":1400.3,"adviced_applied_water":9.9,"air_temperature_24":9.1,"applied_water_avg_10d":1.26,"applied_water_fcdp0":9.932,"applied_water_fcdp1":0,"applied_water_fcdp2":0,"applied_water_fcdp3":0,"applied_water_fcdp4":0,"applied_water_fcdp5":0,"applied_water_fcdp6":0,"applied_water_fcdp7":0,"area_percentage_over_irrigation":0,"area_percentage_requiring_irrigation":100,"attainable_crop_production":16.507,"critical_soil_moisture_root_zone":0.116,"crop_production_cumulative":94190,"crop_production_percentile5":9.681,"crop_production_percentile95":16.989,"et_fcdp0":0.446,"et_fcdp1":0.298,"et_fcdp2":0.332,"et_fcdp3":0.97,"et_fcdp4":0.698,"et_fcdp5":0.694,"et_fcdp6":0.7,"et_fcdp7":0.708,"field_efficiency_avg_10d":84,"forecast_et0_8days_sum":9.19,"fullness":12,"irrigation_amount_cumulative":1937.66,"irrigation_yesno":1,"leaf_nitrogen":1.136,"leaf_water_potential":-17.935,"ls_day":0,"moisture_content_cane":66.639,"net_carbon_supply_in_soil":1.2335,"ndvi":0.38,"organic_matter":1.77,"penmann_monteith_crop_coefficient_kc_avg_10d":0.66,"penmann_monteith_reference_et0":1,"potential_transpiration":0.2,"precipitation_avg_10d":1.69,"precipitation_cumulative":913.89,"precipitation_fcdp0":2.8,"precipitation_fcdp1":39.7,"precipitation_fcdp2":3.2,"precipitation_fcdp3":0,"precipitation_fcdp4":23,"precipitation_fcdp5":0,"precipitation_fcdp6":0.5,"precipitation_fcdp7":0.25,"production_gap":2.706,"quality_per":100,"relative_humidity_24":79.1,"root_depth":1069,"s2_day":1,"soil_moisture_holding_capacity":136,"soil_moisture_percentile5":0.119,"soil_moisture_percentile95":0.123,"soil_moisture_root_zone":0.121,"soil_moisture_root_zone_irri_fcdp0":0.136,"soil_moisture_root_zone_irri_fcdp1":0.157,"soil_moisture_root_zone_irri_fcdp2":0.159,"soil_moisture_root_zone_irri_fcdp3":0.158,"soil_moisture_root_zone_irri_fcdp4":0.171,"soil_moisture_root_zone_irri_fcdp5":0.171,"soil_moisture_root_zone_irri_fcdp6":0.17,"soil_moisture_root_zone_irri_fcdp7":0.17,"soil_moisture_root_zone_no_irri_fcdp0":0.123,"soil_moisture_root_zone_no_irri_fcdp1":0.144,"soil_moisture_root_zone_no_irri_fcdp2":0.146,"soil_moisture_root_zone_no_irri_fcdp3":0.145,"soil_moisture_root_zone_no_irri_fcdp4":0.159,"soil_moisture_root_zone_no_irri_fcdp5":0.159,"soil_moisture_root_zone_no_irri_fcdp6":0.158,"soil_moisture_root_zone_no_irri_fcdp7":0.158,"soil_temperature":13.408,"soil_water_potential_critical":-1000,"soil_water_potential_fc":-100,"soil_water_potential_percentile5":-816.798,"soil_water_potential_percentile95":-677.328,"soil_water_potential_root_zone":-736.2,"solar_radiation_cumulative":178583.2,"stomatal_conductance":2.6,"sugar_content_cane":15.967,"thermal_degrees_days_cumulative":9629.391,"thermal_update":1,"theta_fc_sub":0.24,"theta_sat_sub":0.426,"theta_wp_sub":0.104,"time_until_next_irrigation":0,"uniformity_soil_moisture":0.008,"uniformity_vegetation_cover_stdmean":0.108,"utc_ls_datetime":"2025-01-28 18:40","utc_s2_datetime":"2025-01-30 18:45","vegetation_cover":40.9,"vegetation_cover_percentile5":32.9,"vegetation_cover_percentile95":47.1,"visible_update":0,"water_productivity_avg_10d":2.38,"water_unlimited_crop_production":13.8},"3a5c029c-75a9-4962-8921-aa1794b9e9e4":{"name":"Field 5_22x18 Non pareil, carmel, aldrich.","date":"2025-01-30","actual_crop_production":6,"actual_evapotranspiration":0.1,"actual_evapotranspiration_applied_water":0.02,"actual_evapotranspiration_applied_water_cumulative":394.15,"actual_evapotranspiration_cumulative":820.21,"actual_transpiration":0,"actual_transpiration_cumulative":348.8,"adviced_applied_water":7.7,"air_temperature_24":9.1,"applied_water_avg_10d":0.28,"applied_water_fcdp0":7.704,"applied_water_fcdp1":0,"applied_water_fcdp2":0,"applied_water_fcdp3":0,"applied_water_fcdp4":0,"applied_water_fcdp5":0,"applied_water_fcdp6":0,"applied_water_fcdp7":0,"area_percentage_over_irrigation":0,"area_percentage_requiring_irrigation":100,"attainable_crop_production":10.843,"critical_soil_moisture_root_zone":0.114,"crop_production_cumulative":14019,"crop_production_percentile5":3.521,"crop_production_percentile95":7.883,"et_fcdp0":0.202,"et_fcdp1":0.135,"et_fcdp2":0.151,"et_fcdp3":0.44,"et_fcdp4":0.315,"et_fcdp5":0.316,"et_fcdp6":0.318,"et_fcdp7":0.321,"field_efficiency_avg_10d":65,"forecast_et0_8days_sum":9.28,"fullness":8,"irrigation_amount_cumulative":603.71,"irrigation_yesno":1,"leaf_nitrogen":1.043,"leaf_water_potential":-12.328,"ls_day":0,"moisture_content_cane":66.768,"net_carbon_supply_in_soil":1.1729,"ndvi":0.28,"organic_matter":1.782,"penmann_monteith_crop_coefficient_kc_avg_10d":0.32,"penmann_monteith_reference_et0":1,"potential_transpiration":0.1,"precipitation_avg_10d":1.69,"precipitation_cumulative":913.89,"precipitation_fcdp0":2.8,"precipitation_fcdp1":39.7,"precipitation_fcdp2":3.2,"precipitation_fcdp3":0,"precipitation_fcdp4":23,"precipitation_fcdp5":0,"precipitation_fcdp6":0.5,"precipitation_fcdp7":0.25,"production_gap":4.839,"quality_per":100,"relative_humidity_24":79.1,"root_depth":758,"s2_day":1,"soil_moisture_holding_capacity":135,"soil_moisture_percentile5":0.115,"soil_moisture_percentile95":0.118,"soil_moisture_root_zone":0.116,"soil_moisture_root_zone_irri_fcdp0":0.137,"soil_moisture_root_zone_irri_fcdp1":0.161,"soil_moisture_root_zone_irri_fcdp2":0.164,"soil_moisture_root_zone_irri_fcdp3":0.164,"soil_moisture_root_zone_irri_fcdp4":0.18,"soil_moisture_root_zone_irri_fcdp5":0.18,"soil_moisture_root_zone_irri_fcdp6":0.18,"soil_moisture_root_zone_irri_fcdp7":0.179,"soil_moisture_root_zone_no_irri_fcdp0":0.119,"soil_moisture_root_zone_no_irri_fcdp1":0.144,"soil_moisture_root_zone_no_irri_fcdp2":0.147,"soil_moisture_root_zone_no_irri_fcdp3":0.146,"soil_moisture_root_zone_no_irri_fcdp4":0.163,"soil_moisture_root_zone_no_irri_fcdp5":0.163,"soil_moisture_root_zone_no_irri_fcdp6":0.163,"soil_moisture_root_zone_no_irri_fcdp7":0.163,"soil_temperature":13.541,"soil_water_potential_critical":-1000,"soil_water_potential_fc":-100,"soil_water_potential_percentile5":-921.565,"soil_water_potential_percentile95":-763.95,"soil_water_potential_root_zone":-850.5,"solar_radiation_cumulative":178581.2,"stomatal_conductance":1.64,"sugar_content_cane":15.863,"thermal_degrees_days_cumulative":9629.392,"thermal_update":1,"theta_fc_sub":0.237,"theta_sat_sub":0.425,"theta_wp_sub":0.102,"time_until_next_irrigation":0,"uniformity_soil_moisture":0.009,"uniformity_vegetation_cover_stdmean":0.148,"utc_ls_datetime":"2025-01-28 18:40","utc_s2_datetime":"2025-01-30 18:45","vegetation_cover":25,"vegetation_cover_percentile5":17.9,"vegetation_cover_percentile95":30.5,"visible_update":0,"water_productivity_avg_10d":2.44,"water_unlimited_crop_production":9.5},"2b61a1b6-9801-4e48-9d05-1c9d12549424":{"name":"Field 7_Tulare Walnuts 22x18","date":"2025-01-30","actual_crop_production":1.9,"actual_evapotranspiration":0.3,"actual_evapotranspiration_applied_water":0.15,"actual_evapotranspiration_applied_water_cumulative":729.61,"actual_evapotranspiration_cumulative":1625.26,"actual_transpiration":0,"actual_transpiration_cumulative":979.2,"adviced_applied_water":5.7,"air_temperature_24":9.1,"applied_water_avg_10d":0.95,"applied_water_fcdp0":5.684,"applied_water_fcdp1":0,"applied_water_fcdp2":0,"applied_water_fcdp3":0,"applied_water_fcdp4":0,"applied_water_fcdp5":0,"applied_water_fcdp6":0,"applied_water_fcdp7":0,"area_percentage_over_irrigation":0,"area_percentage_requiring_irrigation":100,"attainable_crop_production":6.646,"critical_soil_moisture_root_zone":0.123,"crop_production_cumulative":56269,"crop_production_percentile5":1.168,"crop_production_percentile95":3.177,"et_fcdp0":0.41,"et_fcdp1":0.274,"et_fcdp2":0.306,"et_fcdp3":0.892,"et_fcdp4":0.643,"et_fcdp5":0.639,"et_fcdp6":0.644,"et_fcdp7":0.651,"field_efficiency_avg_10d":76,"forecast_et0_8days_sum":9.18,"fullness":8,"irrigation_amount_cumulative":999.62,"irrigation_yesno":1,"leaf_nitrogen":0.978,"leaf_water_potential":-26.323,"ls_day":0,"moisture_content_cane":67.681,"net_carbon_supply_in_soil":1.0581,"ndvi":0.19,"organic_matter":1.44,"penmann_monteith_crop_coefficient_kc_avg_10d":0.58,"penmann_monteith_reference_et0":1,"potential_transpiration":0.1,"precipitation_avg_10d":1.69,"precipitation_cumulative":913.89,"precipitation_fcdp0":2.8,"precipitation_fcdp1":39.7,"precipitation_fcdp2":3.2,"precipitation_fcdp3":0,"precipitation_fcdp4":23,"precipitation_fcdp5":0,"precipitation_fcdp6":0.5,"precipitation_fcdp7":0.25,"production_gap":4.793,"quality_per":100,"relative_humidity_24":79.1,"root_depth":1152,"s2_day":1,"soil_moisture_holding_capacity":137,"soil_moisture_percentile5":0.119,"soil_moisture_percentile95":0.122,"soil_moisture_root_zone":0.12,"soil_moisture_root_zone_irri_fcdp0":0.134,"soil_moisture_root_zone_irri_fcdp1":0.148,"soil_moisture_root_zone_irri_fcdp2":0.15,"soil_moisture_root_zone_irri_fcdp3":0.15,"soil_moisture_root_zone_irri_fcdp4":0.16,"soil_moisture_root_zone_irri_fcdp5":0.159,"soil_moisture_root_zone_irri_fcdp6":0.159,"soil_moisture_root_zone_irri_fcdp7":0.159,"soil_moisture_root_zone_no_irri_fcdp0":0.122,"soil_moisture_root_zone_no_irri_fcdp1":0.137,"soil_moisture_root_zone_no_irri_fcdp2":0.139,"soil_moisture_root_zone_no_irri_fcdp3":0.138,"soil_moisture_root_zone_no_irri_fcdp4":0.149,"soil_moisture_root_zone_no_irri_fcdp5":0.148,"soil_moisture_root_zone_no_irri_fcdp6":0.148,"soil_moisture_root_zone_no_irri_fcdp7":0.147,"soil_temperature":12.106,"soil_water_potential_critical":-750,"soil_water_potential_fc":-100,"soil_water_potential_percentile5":-965.678,"soil_water_potential_percentile95":-816.852,"soil_water_potential_root_zone":-898.6,"solar_radiation_cumulative":178585.7,"stomatal_conductance":1.68,"sugar_content_cane":15.131,"thermal_degrees_days_cumulative":7623.976,"thermal_update":1,"theta_fc_sub":0.243,"theta_sat_sub":0.428,"theta_wp_sub":0.106,"time_until_next_irrigation":0,"uniformity_soil_moisture":0,"uniformity_vegetation_cover_stdmean":0.245,"utc_ls_datetime":"2025-01-28 18:40","utc_s2_datetime":"2025-01-30 18:45","vegetation_cover":10.6,"vegetation_cover_percentile5":7.8,"vegetation_cover_percentile95":15.5,"visible_update":0,"water_productivity_avg_10d":0.4,"water_unlimited_crop_production":4.9},"d705dcb2-6f17-42ba-a488-96f56d7b1e1c":{"name":"Field 4B_22x18 NP, Carmel, Aldrich","date":"2025-01-30","actual_crop_production":7.6,"actual_evapotranspiration":0.2,"actual_evapotranspiration_applied_water":0.04,"actual_evapotranspiration_applied_water_cumulative":453.5,"actual_evapotranspiration_cumulative":897.91,"actual_transpiration":0.1,"actual_transpiration_cumulative":423.4,"adviced_applied_water":8.2,"air_temperature_24":9.1,"applied_water_avg_10d":0.59,"applied_water_fcdp0":8.172,"applied_water_fcdp1":0,"applied_water_fcdp2":0,"applied_water_fcdp3":0,"applied_water_fcdp4":0,"applied_water_fcdp5":0,"applied_water_fcdp6":0,"applied_water_fcdp7":0,"area_percentage_over_irrigation":0,"area_percentage_requiring_irrigation":100,"attainable_crop_production":9.513,"critical_soil_moisture_root_zone":0.122,"crop_production_cumulative":18772,"crop_production_percentile5":5.694,"crop_production_percentile95":9.76,"et_fcdp0":0.309,"et_fcdp1":0.207,"et_fcdp2":0.231,"et_fcdp3":0.673,"et_fcdp4":0.484,"et_fcdp5":0.482,"et_fcdp6":0.486,"et_fcdp7":0.491,"field_efficiency_avg_10d":81,"forecast_et0_8days_sum":9.21,"fullness":10,"irrigation_amount_cumulative":712.56,"irrigation_yesno":1,"leaf_nitrogen":1.073,"leaf_water_potential":-16.781,"ls_day":0,"moisture_content_cane":66.537,"net_carbon_supply_in_soil":1.0954,"ndvi":0.3,"organic_matter":2.184,"penmann_monteith_crop_coefficient_kc_avg_10d":0.48,"penmann_monteith_reference_et0":1,"potential_transpiration":0.1,"precipitation_avg_10d":1.69,"precipitation_cumulative":913.89,"precipitation_fcdp0":2.8,"precipitation_fcdp1":39.7,"precipitation_fcdp2":3.2,"precipitation_fcdp3":0,"precipitation_fcdp4":23,"precipitation_fcdp5":0,"precipitation_fcdp6":0.5,"precipitation_fcdp7":0.25,"production_gap":1.909,"quality_per":100,"relative_humidity_24":79.1,"root_depth":777,"s2_day":1,"soil_moisture_holding_capacity":139,"soil_moisture_percentile5":0.124,"soil_moisture_percentile95":0.127,"soil_moisture_root_zone":0.126,"soil_moisture_root_zone_irri_fcdp0":0.146,"soil_moisture_root_zone_irri_fcdp1":0.17,"soil_moisture_root_zone_irri_fcdp2":0.173,"soil_moisture_root_zone_irri_fcdp3":0.172,"soil_moisture_root_zone_irri_fcdp4":0.188,"soil_moisture_root_zone_irri_fcdp5":0.187,"soil_moisture_root_zone_irri_fcdp6":0.187,"soil_moisture_root_zone_irri_fcdp7":0.187,"soil_moisture_root_zone_no_irri_fcdp0":0.128,"soil_moisture_root_zone_no_irri_fcdp1":0.153,"soil_moisture_root_zone_no_irri_fcdp2":0.156,"soil_moisture_root_zone_no_irri_fcdp3":0.155,"soil_moisture_root_zone_no_irri_fcdp4":0.172,"soil_moisture_root_zone_no_irri_fcdp5":0.171,"soil_moisture_root_zone_no_irri_fcdp6":0.171,"soil_moisture_root_zone_no_irri_fcdp7":0.17,"soil_temperature":13.059,"soil_water_potential_critical":-1000,"soil_water_potential_fc":-100,"soil_water_potential_percentile5":-891.358,"soil_water_potential_percentile95":-747.703,"soil_water_potential_root_zone":-799.5,"solar_radiation_cumulative":178581.4,"stomatal_conductance":2.02,"sugar_content_cane":16.048,"thermal_degrees_days_cumulative":9633.891,"thermal_update":1,"theta_fc_sub":0.247,"theta_sat_sub":0.43,"theta_wp_sub":0.108,"time_until_next_irrigation":0,"uniformity_soil_moisture":0.008,"uniformity_vegetation_cover_stdmean":0.102,"utc_ls_datetime":"2025-01-28 18:40","utc_s2_datetime":"2025-01-30 18:45","vegetation_cover":28.4,"vegetation_cover_percentile5":23.7,"vegetation_cover_percentile95":33.6,"visible_update":0,"water_productivity_avg_10d":2.08,"water_unlimited_crop_production":8.3}}