{"8f95e554-5a9b-4fe5-a046-947e978e3867":{"name":"Field 1_Walnuts Tulare","date":"2025-10-04","actual_crop_production":30.8,"actual_evapotranspiration":0.7,"actual_evapotranspiration_applied_water":0.12,"actual_evapotranspiration_applied_water_cumulative":589.87,"actual_evapotranspiration_cumulative":1112.35,"actual_transpiration":0.3,"actual_transpiration_cumulative":465.3,"adviced_applied_water":9.8,"air_temperature_24":6.4,"applied_water_avg_10d":0.09,"applied_water_fcdp0":9.846,"applied_water_fcdp1":0,"applied_water_fcdp2":0,"applied_water_fcdp3":0,"applied_water_fcdp4":0,"applied_water_fcdp5":0,"applied_water_fcdp6":0,"applied_water_fcdp7":9.838,"area_percentage_over_irrigation":0,"area_percentage_requiring_irrigation":100,"attainable_crop_production":42.113,"critical_soil_moisture_root_zone":0.114,"crop_production_cumulative":18042,"crop_production_percentile5":17.044,"crop_production_percentile95":41.358,"et_fcdp0":0.664,"et_fcdp1":0.683,"et_fcdp2":0.73,"et_fcdp3":0.741,"et_fcdp4":0.686,"et_fcdp5":0.552,"et_fcdp6":0.622,"et_fcdp7":0.486,"field_efficiency_avg_10d":0,"forecast_et0_8days_sum":10.55,"fullness":9,"irrigation_amount_cumulative":854.71,"irrigation_yesno":1,"leaf_nitrogen":1.208,"leaf_water_potential":-57.523,"ls_day":1,"moisture_content_cane":67.115,"net_carbon_supply_in_soil":2.0332,"ndvi":0.42,"organic_matter":1.522,"penmann_monteith_crop_coefficient_kc_avg_10d":0.35,"penmann_monteith_reference_et0":1.5,"potential_transpiration":0.3,"precipitation_avg_10d":1.61,"precipitation_cumulative":896.99,"precipitation_fcdp0":0,"precipitation_fcdp1":0,"precipitation_fcdp2":0,"precipitation_fcdp3":0,"precipitation_fcdp4":0,"precipitation_fcdp5":0,"precipitation_fcdp6":0,"precipitation_fcdp7":0,"production_gap":11.322,"quality_per":100,"relative_humidity_24":58.9,"root_depth":790,"s2_day":0,"soil_moisture_holding_capacity":132,"soil_moisture_percentile5":0.11,"soil_moisture_percentile95":0.114,"soil_moisture_root_zone":0.112,"soil_moisture_root_zone_irri_fcdp0":0.129,"soil_moisture_root_zone_irri_fcdp1":0.128,"soil_moisture_root_zone_irri_fcdp2":0.127,"soil_moisture_root_zone_irri_fcdp3":0.126,"soil_moisture_root_zone_irri_fcdp4":0.125,"soil_moisture_root_zone_irri_fcdp5":0.124,"soil_moisture_root_zone_irri_fcdp6":0.124,"soil_moisture_root_zone_irri_fcdp7":0.14,"soil_moisture_root_zone_no_irri_fcdp0":0.112,"soil_moisture_root_zone_no_irri_fcdp1":0.111,"soil_moisture_root_zone_no_irri_fcdp2":0.11,"soil_moisture_root_zone_no_irri_fcdp3":0.109,"soil_moisture_root_zone_no_irri_fcdp4":0.108,"soil_moisture_root_zone_no_irri_fcdp5":0.108,"soil_moisture_root_zone_no_irri_fcdp6":0.107,"soil_moisture_root_zone_no_irri_fcdp7":0.107,"soil_temperature":10.757,"soil_water_potential_critical":-750,"soil_water_potential_fc":-100,"soil_water_potential_percentile5":-988.161,"soil_water_potential_percentile95":-756.334,"soil_water_potential_root_zone":-848.6,"solar_radiation_cumulative":176237.2,"stomatal_conductance":3.11,"sugar_content_cane":15.585,"thermal_degrees_days_cumulative":7600.976,"thermal_update":1,"theta_fc_sub":0.231,"theta_sat_sub":0.423,"theta_wp_sub":0.099,"time_until_next_irrigation":0,"uniformity_soil_moisture":0.009,"uniformity_vegetation_cover_stdmean":0.161,"utc_ls_datetime":"2025-01-12 18:40","utc_s2_datetime":"2025-01-10 18:46","vegetation_cover":40.3,"vegetation_cover_percentile5":27.9,"vegetation_cover_percentile95":49.8,"visible_update":1,"water_productivity_avg_10d":4.62,"water_unlimited_crop_production":35.2},"2b61a1b6-9801-4e48-9d05-1c9d12549424":{"name":"Field 7_Tulare Walnuts 22x18","date":"2025-10-04","actual_crop_production":7.2,"actual_evapotranspiration":0.3,"actual_evapotranspiration_applied_water":0.2,"actual_evapotranspiration_applied_water_cumulative":723.73,"actual_evapotranspiration_cumulative":1613.49,"actual_transpiration":0.1,"actual_transpiration_cumulative":977.6,"adviced_applied_water":6.5,"air_temperature_24":6.4,"applied_water_avg_10d":0.23,"applied_water_fcdp0":6.511,"applied_water_fcdp1":0,"applied_water_fcdp2":0,"applied_water_fcdp3":0,"applied_water_fcdp4":0,"applied_water_fcdp5":0,"applied_water_fcdp6":0,"applied_water_fcdp7":6.511,"area_percentage_over_irrigation":0,"area_percentage_requiring_irrigation":100,"attainable_crop_production":20.343,"critical_soil_moisture_root_zone":0.123,"crop_production_cumulative":56209,"crop_production_percentile5":5.397,"crop_production_percentile95":11.39,"et_fcdp0":0.486,"et_fcdp1":0.5,"et_fcdp2":0.534,"et_fcdp3":0.542,"et_fcdp4":0.502,"et_fcdp5":0.404,"et_fcdp6":0.455,"et_fcdp7":0.392,"field_efficiency_avg_10d":0,"forecast_et0_8days_sum":10.52,"fullness":7,"irrigation_amount_cumulative":987.18,"irrigation_yesno":1,"leaf_nitrogen":0.968,"leaf_water_potential":-36.102,"ls_day":1,"moisture_content_cane":68.301,"net_carbon_supply_in_soil":1.2678,"ndvi":0.24,"organic_matter":1.44,"penmann_monteith_crop_coefficient_kc_avg_10d":0.33,"penmann_monteith_reference_et0":1.5,"potential_transpiration":0.2,"precipitation_avg_10d":1.61,"precipitation_cumulative":896.99,"precipitation_fcdp0":0,"precipitation_fcdp1":0,"precipitation_fcdp2":0,"precipitation_fcdp3":0,"precipitation_fcdp4":0,"precipitation_fcdp5":0,"precipitation_fcdp6":0,"precipitation_fcdp7":0,"production_gap":13.181,"quality_per":100,"relative_humidity_24":58.9,"root_depth":1152,"s2_day":0,"soil_moisture_holding_capacity":137,"soil_moisture_percentile5":0.116,"soil_moisture_percentile95":0.119,"soil_moisture_root_zone":0.117,"soil_moisture_root_zone_irri_fcdp0":0.128,"soil_moisture_root_zone_irri_fcdp1":0.128,"soil_moisture_root_zone_irri_fcdp2":0.127,"soil_moisture_root_zone_irri_fcdp3":0.127,"soil_moisture_root_zone_irri_fcdp4":0.127,"soil_moisture_root_zone_irri_fcdp5":0.126,"soil_moisture_root_zone_irri_fcdp6":0.126,"soil_moisture_root_zone_irri_fcdp7":0.137,"soil_moisture_root_zone_no_irri_fcdp0":0.117,"soil_moisture_root_zone_no_irri_fcdp1":0.116,"soil_moisture_root_zone_no_irri_fcdp2":0.116,"soil_moisture_root_zone_no_irri_fcdp3":0.115,"soil_moisture_root_zone_no_irri_fcdp4":0.115,"soil_moisture_root_zone_no_irri_fcdp5":0.115,"soil_moisture_root_zone_no_irri_fcdp6":0.114,"soil_moisture_root_zone_no_irri_fcdp7":0.114,"soil_temperature":11.119,"soil_water_potential_critical":-750,"soil_water_potential_fc":-100,"soil_water_potential_percentile5":-1207.119,"soil_water_potential_percentile95":-980.719,"soil_water_potential_root_zone":-1133.5,"solar_radiation_cumulative":176240.2,"stomatal_conductance":1.88,"sugar_content_cane":14.634,"thermal_degrees_days_cumulative":7607.976,"thermal_update":1,"theta_fc_sub":0.243,"theta_sat_sub":0.428,"theta_wp_sub":0.106,"time_until_next_irrigation":0,"uniformity_soil_moisture":0,"uniformity_vegetation_cover_stdmean":0.176,"utc_ls_datetime":"2025-01-12 18:40","utc_s2_datetime":"2025-01-10 18:46","vegetation_cover":16.5,"vegetation_cover_percentile5":13.8,"vegetation_cover_percentile95":22.8,"visible_update":1,"water_productivity_avg_10d":0.79,"water_unlimited_crop_production":15.6},"b77e3506-6854-4ecc-8758-8bc465f83b15":{"name":"Field 6 BS_22x18 Non pareil and Fritz","date":"2025-10-04","actual_crop_production":55.8,"actual_evapotranspiration":0.9,"actual_evapotranspiration_applied_water":0.31,"actual_evapotranspiration_applied_water_cumulative":1461.16,"actual_evapotranspiration_cumulative":2480.91,"actual_transpiration":0.4,"actual_transpiration_cumulative":1602.6,"adviced_applied_water":12.7,"air_temperature_24":6.4,"applied_water_avg_10d":0.39,"applied_water_fcdp0":12.656,"applied_water_fcdp1":0,"applied_water_fcdp2":0,"applied_water_fcdp3":0,"applied_water_fcdp4":0,"applied_water_fcdp5":0,"applied_water_fcdp6":0,"applied_water_fcdp7":0,"area_percentage_over_irrigation":0,"area_percentage_requiring_irrigation":72,"attainable_crop_production":63.51,"critical_soil_moisture_root_zone":0.116,"crop_production_cumulative":104982,"crop_production_percentile5":45.596,"crop_production_percentile95":65.034,"et_fcdp0":0.818,"et_fcdp1":0.846,"et_fcdp2":0.903,"et_fcdp3":0.916,"et_fcdp4":0.848,"et_fcdp5":0.688,"et_fcdp6":0.769,"et_fcdp7":0.777,"field_efficiency_avg_10d":0,"forecast_et0_8days_sum":10.92,"fullness":17,"irrigation_amount_cumulative":2097.97,"irrigation_yesno":1,"leaf_nitrogen":1.44,"leaf_water_potential":-51.203,"ls_day":1,"moisture_content_cane":68.779,"net_carbon_supply_in_soil":2.5414,"ndvi":0.51,"organic_matter":1.85,"penmann_monteith_crop_coefficient_kc_avg_10d":0.41,"penmann_monteith_reference_et0":1.5,"potential_transpiration":0.4,"precipitation_avg_10d":1.61,"precipitation_cumulative":896.99,"precipitation_fcdp0":0,"precipitation_fcdp1":0,"precipitation_fcdp2":0,"precipitation_fcdp3":0,"precipitation_fcdp4":0,"precipitation_fcdp5":0,"precipitation_fcdp6":0,"precipitation_fcdp7":0,"production_gap":7.719,"quality_per":100,"relative_humidity_24":58.9,"root_depth":1076,"s2_day":0,"soil_moisture_holding_capacity":135,"soil_moisture_percentile5":0.124,"soil_moisture_percentile95":0.132,"soil_moisture_root_zone":0.128,"soil_moisture_root_zone_irri_fcdp0":0.14,"soil_moisture_root_zone_irri_fcdp1":0.139,"soil_moisture_root_zone_irri_fcdp2":0.138,"soil_moisture_root_zone_irri_fcdp3":0.137,"soil_moisture_root_zone_irri_fcdp4":0.136,"soil_moisture_root_zone_irri_fcdp5":0.136,"soil_moisture_root_zone_irri_fcdp6":0.135,"soil_moisture_root_zone_irri_fcdp7":0.134,"soil_moisture_root_zone_no_irri_fcdp0":0.127,"soil_moisture_root_zone_no_irri_fcdp1":0.126,"soil_moisture_root_zone_no_irri_fcdp2":0.125,"soil_moisture_root_zone_no_irri_fcdp3":0.125,"soil_moisture_root_zone_no_irri_fcdp4":0.124,"soil_moisture_root_zone_no_irri_fcdp5":0.123,"soil_moisture_root_zone_no_irri_fcdp6":0.122,"soil_moisture_root_zone_no_irri_fcdp7":0.122,"soil_temperature":10.875,"soil_water_potential_critical":-1000,"soil_water_potential_fc":-100,"soil_water_potential_percentile5":-620.565,"soil_water_potential_percentile95":-457.692,"soil_water_potential_root_zone":-537.1,"solar_radiation_cumulative":176250.5,"stomatal_conductance":3.96,"sugar_content_cane":14.251,"thermal_degrees_days_cumulative":9583.686,"thermal_update":1,"theta_fc_sub":0.239,"theta_sat_sub":0.426,"theta_wp_sub":0.104,"time_until_next_irrigation":0,"uniformity_soil_moisture":0.016,"uniformity_vegetation_cover_stdmean":0.071,"utc_ls_datetime":"2025-01-12 18:40","utc_s2_datetime":"2025-01-10 18:46","vegetation_cover":60.4,"vegetation_cover_percentile5":53.2,"vegetation_cover_percentile95":66.4,"visible_update":1,"water_productivity_avg_10d":7.55,"water_unlimited_crop_production":55.8},"d705dcb2-6f17-42ba-a488-96f56d7b1e1c":{"name":"Field 4B_22x18 NP, Carmel, Aldrich","date":"2025-10-04","actual_crop_production":27.8,"actual_evapotranspiration":0.6,"actual_evapotranspiration_applied_water":0.13,"actual_evapotranspiration_applied_water_cumulative":451.09,"actual_evapotranspiration_cumulative":887.94,"actual_transpiration":0.2,"actual_transpiration_cumulative":419.6,"adviced_applied_water":9.7,"air_temperature_24":6.4,"applied_water_avg_10d":0.12,"applied_water_fcdp0":9.692,"applied_water_fcdp1":0,"applied_water_fcdp2":0,"applied_water_fcdp3":0,"applied_water_fcdp4":0,"applied_water_fcdp5":0,"applied_water_fcdp6":0,"applied_water_fcdp7":0,"area_percentage_over_irrigation":0,"area_percentage_requiring_irrigation":100,"attainable_crop_production":31.85,"critical_soil_moisture_root_zone":0.122,"crop_production_cumulative":18495,"crop_production_percentile5":22.687,"crop_production_percentile95":32.907,"et_fcdp0":0.585,"et_fcdp1":0.602,"et_fcdp2":0.643,"et_fcdp3":0.653,"et_fcdp4":0.604,"et_fcdp5":0.487,"et_fcdp6":0.548,"et_fcdp7":0.536,"field_efficiency_avg_10d":0,"forecast_et0_8days_sum":10.59,"fullness":12,"irrigation_amount_cumulative":705.82,"irrigation_yesno":1,"leaf_nitrogen":1.101,"leaf_water_potential":-40.582,"ls_day":1,"moisture_content_cane":66.512,"net_carbon_supply_in_soil":1.7648,"ndvi":0.37,"organic_matter":2.184,"penmann_monteith_crop_coefficient_kc_avg_10d":0.32,"penmann_monteith_reference_et0":1.5,"potential_transpiration":0.2,"precipitation_avg_10d":1.61,"precipitation_cumulative":896.99,"precipitation_fcdp0":0,"precipitation_fcdp1":0,"precipitation_fcdp2":0,"precipitation_fcdp3":0,"precipitation_fcdp4":0,"precipitation_fcdp5":0,"precipitation_fcdp6":0,"precipitation_fcdp7":0,"production_gap":4.046,"quality_per":100,"relative_humidity_24":58.9,"root_depth":777,"s2_day":0,"soil_moisture_holding_capacity":139,"soil_moisture_percentile5":0.124,"soil_moisture_percentile95":0.129,"soil_moisture_root_zone":0.127,"soil_moisture_root_zone_irri_fcdp0":0.143,"soil_moisture_root_zone_irri_fcdp1":0.143,"soil_moisture_root_zone_irri_fcdp2":0.142,"soil_moisture_root_zone_irri_fcdp3":0.141,"soil_moisture_root_zone_irri_fcdp4":0.14,"soil_moisture_root_zone_irri_fcdp5":0.139,"soil_moisture_root_zone_irri_fcdp6":0.139,"soil_moisture_root_zone_irri_fcdp7":0.138,"soil_moisture_root_zone_no_irri_fcdp0":0.126,"soil_moisture_root_zone_no_irri_fcdp1":0.125,"soil_moisture_root_zone_no_irri_fcdp2":0.124,"soil_moisture_root_zone_no_irri_fcdp3":0.123,"soil_moisture_root_zone_no_irri_fcdp4":0.123,"soil_moisture_root_zone_no_irri_fcdp5":0.122,"soil_moisture_root_zone_no_irri_fcdp6":0.121,"soil_moisture_root_zone_no_irri_fcdp7":0.12,"soil_temperature":11.203,"soil_water_potential_critical":-1000,"soil_water_potential_fc":-100,"soil_water_potential_percentile5":-867.507,"soil_water_potential_percentile95":-685.202,"soil_water_potential_root_zone":-769.6,"solar_radiation_cumulative":176236.2,"stomatal_conductance":3.09,"sugar_content_cane":16.069,"thermal_degrees_days_cumulative":9583.687,"thermal_update":1,"theta_fc_sub":0.247,"theta_sat_sub":0.43,"theta_wp_sub":0.108,"time_until_next_irrigation":0,"uniformity_soil_moisture":0.016,"uniformity_vegetation_cover_stdmean":0.069,"utc_ls_datetime":"2025-01-12 18:40","utc_s2_datetime":"2025-01-10 18:46","vegetation_cover":39.2,"vegetation_cover_percentile5":35.1,"vegetation_cover_percentile95":43.4,"visible_update":1,"water_productivity_avg_10d":4.7,"water_unlimited_crop_production":27.8},"c715d69c-8aa3-44a1-9c1f-8c88810fd362":{"name":"Field 3N_22x18 Butte and padre","date":"2025-10-04","actual_crop_production":36.5,"actual_evapotranspiration":0.9,"actual_evapotranspiration_applied_water":0.28,"actual_evapotranspiration_applied_water_cumulative":1353.46,"actual_evapotranspiration_cumulative":2199.89,"actual_transpiration":0.3,"actual_transpiration_cumulative":1299.8,"adviced_applied_water":10.6,"air_temperature_24":6.4,"applied_water_avg_10d":0.21,"applied_water_fcdp0":10.596,"applied_water_fcdp1":0,"applied_water_fcdp2":0,"applied_water_fcdp3":0,"applied_water_fcdp4":0,"applied_water_fcdp5":0,"applied_water_fcdp6":0,"applied_water_fcdp7":0,"area_percentage_over_irrigation":0,"area_percentage_requiring_irrigation":99,"attainable_crop_production":42.386,"critical_soil_moisture_root_zone":0.117,"crop_production_cumulative":85648,"crop_production_percentile5":27.435,"crop_production_percentile95":43.513,"et_fcdp0":0.751,"et_fcdp1":0.77,"et_fcdp2":0.823,"et_fcdp3":0.836,"et_fcdp4":0.774,"et_fcdp5":0.62,"et_fcdp6":0.702,"et_fcdp7":0.708,"field_efficiency_avg_10d":0,"forecast_et0_8days_sum":10.31,"fullness":14,"irrigation_amount_cumulative":1931.54,"irrigation_yesno":1,"leaf_nitrogen":1.193,"leaf_water_potential":-53.182,"ls_day":1,"moisture_content_cane":67.335,"net_carbon_supply_in_soil":1.9929,"ndvi":0.41,"organic_matter":1.814,"penmann_monteith_crop_coefficient_kc_avg_10d":0.41,"penmann_monteith_reference_et0":1.5,"potential_transpiration":0.3,"precipitation_avg_10d":1.61,"precipitation_cumulative":896.99,"precipitation_fcdp0":0,"precipitation_fcdp1":0,"precipitation_fcdp2":0,"precipitation_fcdp3":0,"precipitation_fcdp4":0,"precipitation_fcdp5":0,"precipitation_fcdp6":0,"precipitation_fcdp7":0,"production_gap":5.914,"quality_per":100,"relative_humidity_24":58.9,"root_depth":1052,"s2_day":0,"soil_moisture_holding_capacity":136,"soil_moisture_percentile5":0.121,"soil_moisture_percentile95":0.128,"soil_moisture_root_zone":0.125,"soil_moisture_root_zone_irri_fcdp0":0.137,"soil_moisture_root_zone_irri_fcdp1":0.137,"soil_moisture_root_zone_irri_fcdp2":0.136,"soil_moisture_root_zone_irri_fcdp3":0.135,"soil_moisture_root_zone_irri_fcdp4":0.134,"soil_moisture_root_zone_irri_fcdp5":0.134,"soil_moisture_root_zone_irri_fcdp6":0.133,"soil_moisture_root_zone_irri_fcdp7":0.132,"soil_moisture_root_zone_no_irri_fcdp0":0.124,"soil_moisture_root_zone_no_irri_fcdp1":0.123,"soil_moisture_root_zone_no_irri_fcdp2":0.123,"soil_moisture_root_zone_no_irri_fcdp3":0.122,"soil_moisture_root_zone_no_irri_fcdp4":0.121,"soil_moisture_root_zone_no_irri_fcdp5":0.121,"soil_moisture_root_zone_no_irri_fcdp6":0.12,"soil_moisture_root_zone_no_irri_fcdp7":0.119,"soil_temperature":11.169,"soil_water_potential_critical":-1000,"soil_water_potential_fc":-100,"soil_water_potential_percentile5":-787.681,"soil_water_potential_percentile95":-565.023,"soil_water_potential_root_zone":-656,"solar_radiation_cumulative":176231.2,"stomatal_conductance":3.58,"sugar_content_cane":15.409,"thermal_degrees_days_cumulative":9583.687,"thermal_update":1,"theta_fc_sub":0.241,"theta_sat_sub":0.427,"theta_wp_sub":0.105,"time_until_next_irrigation":0,"uniformity_soil_moisture":0.016,"uniformity_vegetation_cover_stdmean":0.074,"utc_ls_datetime":"2025-01-12 18:40","utc_s2_datetime":"2025-01-10 18:46","vegetation_cover":45.7,"vegetation_cover_percentile5":39.2,"vegetation_cover_percentile95":50.8,"visible_update":1,"water_productivity_avg_10d":5.87,"water_unlimited_crop_production":36.5},"62aeadb5-2832-4f0b-9f9c-bd16f823989f":{"name":"Field 6 BN_22x18 Non pareil and Fritz","date":"2025-10-04","actual_crop_production":45.5,"actual_evapotranspiration":0.9,"actual_evapotranspiration_applied_water":0.27,"actual_evapotranspiration_applied_water_cumulative":1479.4,"actual_evapotranspiration_cumulative":2474.75,"actual_transpiration":0.4,"actual_transpiration_cumulative":1640.1,"adviced_applied_water":11.6,"air_temperature_24":6.4,"applied_water_avg_10d":0.37,"applied_water_fcdp0":11.646,"applied_water_fcdp1":0,"applied_water_fcdp2":0,"applied_water_fcdp3":0,"applied_water_fcdp4":0,"applied_water_fcdp5":0,"applied_water_fcdp6":0,"applied_water_fcdp7":0,"area_percentage_over_irrigation":0,"area_percentage_requiring_irrigation":99,"attainable_crop_production":53.683,"critical_soil_moisture_root_zone":0.114,"crop_production_cumulative":105627,"crop_production_percentile5":37.091,"crop_production_percentile95":55.388,"et_fcdp0":0.728,"et_fcdp1":0.75,"et_fcdp2":0.801,"et_fcdp3":0.814,"et_fcdp4":0.753,"et_fcdp5":0.607,"et_fcdp6":0.683,"et_fcdp7":0.69,"field_efficiency_avg_10d":0,"forecast_et0_8days_sum":10.61,"fullness":15,"irrigation_amount_cumulative":2129.5,"irrigation_yesno":1,"leaf_nitrogen":1.294,"leaf_water_potential":-53.696,"ls_day":1,"moisture_content_cane":67.781,"net_carbon_supply_in_soil":2.2874,"ndvi":0.46,"organic_matter":1.776,"penmann_monteith_crop_coefficient_kc_avg_10d":0.39,"penmann_monteith_reference_et0":1.5,"potential_transpiration":0.4,"precipitation_avg_10d":1.61,"precipitation_cumulative":896.99,"precipitation_fcdp0":0,"precipitation_fcdp1":0,"precipitation_fcdp2":0,"precipitation_fcdp3":0,"precipitation_fcdp4":0,"precipitation_fcdp5":0,"precipitation_fcdp6":0,"precipitation_fcdp7":0,"production_gap":8.172,"quality_per":100,"relative_humidity_24":58.9,"root_depth":1068,"s2_day":0,"soil_moisture_holding_capacity":134,"soil_moisture_percentile5":0.119,"soil_moisture_percentile95":0.125,"soil_moisture_root_zone":0.122,"soil_moisture_root_zone_irri_fcdp0":0.134,"soil_moisture_root_zone_irri_fcdp1":0.133,"soil_moisture_root_zone_irri_fcdp2":0.133,"soil_moisture_root_zone_irri_fcdp3":0.132,"soil_moisture_root_zone_irri_fcdp4":0.131,"soil_moisture_root_zone_irri_fcdp5":0.131,"soil_moisture_root_zone_irri_fcdp6":0.13,"soil_moisture_root_zone_irri_fcdp7":0.129,"soil_moisture_root_zone_no_irri_fcdp0":0.121,"soil_moisture_root_zone_no_irri_fcdp1":0.121,"soil_moisture_root_zone_no_irri_fcdp2":0.12,"soil_moisture_root_zone_no_irri_fcdp3":0.119,"soil_moisture_root_zone_no_irri_fcdp4":0.118,"soil_moisture_root_zone_no_irri_fcdp5":0.118,"soil_moisture_root_zone_no_irri_fcdp6":0.117,"soil_moisture_root_zone_no_irri_fcdp7":0.116,"soil_temperature":11.287,"soil_water_potential_critical":-1000,"soil_water_potential_fc":-100,"soil_water_potential_percentile5":-696.122,"soil_water_potential_percentile95":-528.839,"soil_water_potential_root_zone":-613,"solar_radiation_cumulative":176240.1,"stomatal_conductance":3.69,"sugar_content_cane":15.051,"thermal_degrees_days_cumulative":9583.686,"thermal_update":1,"theta_fc_sub":0.236,"theta_sat_sub":0.425,"theta_wp_sub":0.102,"time_until_next_irrigation":0,"uniformity_soil_moisture":0.017,"uniformity_vegetation_cover_stdmean":0.073,"utc_ls_datetime":"2025-01-12 18:40","utc_s2_datetime":"2025-01-10 18:46","vegetation_cover":53.2,"vegetation_cover_percentile5":47.4,"vegetation_cover_percentile95":60.1,"visible_update":1,"water_productivity_avg_10d":6.76,"water_unlimited_crop_production":45.5},"cd78e96c-d5cf-4982-af33-36bd15090453":{"name":"Field 6 A_22x9 Independence","date":"2025-10-04","actual_crop_production":19.3,"actual_evapotranspiration":0.6,"actual_evapotranspiration_applied_water":0.22,"actual_evapotranspiration_applied_water_cumulative":806.48,"actual_evapotranspiration_cumulative":1371.91,"actual_transpiration":0.1,"actual_transpiration_cumulative":662.1,"adviced_applied_water":8.6,"air_temperature_24":6.4,"applied_water_avg_10d":0.18,"applied_water_fcdp0":8.555,"applied_water_fcdp1":0,"applied_water_fcdp2":0,"applied_water_fcdp3":0,"applied_water_fcdp4":0,"applied_water_fcdp5":0,"applied_water_fcdp6":0,"applied_water_fcdp7":5.77,"area_percentage_over_irrigation":0,"area_percentage_requiring_irrigation":100,"attainable_crop_production":27.922,"critical_soil_moisture_root_zone":0.118,"crop_production_cumulative":32121,"crop_production_percentile5":11.05,"crop_production_percentile95":28.888,"et_fcdp0":0.583,"et_fcdp1":0.601,"et_fcdp2":0.642,"et_fcdp3":0.652,"et_fcdp4":0.603,"et_fcdp5":0.486,"et_fcdp6":0.547,"et_fcdp7":0.523,"field_efficiency_avg_10d":0,"forecast_et0_8days_sum":10.62,"fullness":10,"irrigation_amount_cumulative":1125.26,"irrigation_yesno":1,"leaf_nitrogen":1.012,"leaf_water_potential":-40.361,"ls_day":1,"moisture_content_cane":66.393,"net_carbon_supply_in_soil":1.6215,"ndvi":0.32,"organic_matter":1.461,"penmann_monteith_crop_coefficient_kc_avg_10d":0.35,"penmann_monteith_reference_et0":1.5,"potential_transpiration":0.2,"precipitation_avg_10d":1.61,"precipitation_cumulative":896.99,"precipitation_fcdp0":0,"precipitation_fcdp1":0,"precipitation_fcdp2":0,"precipitation_fcdp3":0,"precipitation_fcdp4":0,"precipitation_fcdp5":0,"precipitation_fcdp6":0,"precipitation_fcdp7":0,"production_gap":8.656,"quality_per":100,"relative_humidity_24":58.9,"root_depth":922,"s2_day":0,"soil_moisture_holding_capacity":137,"soil_moisture_percentile5":0.117,"soil_moisture_percentile95":0.123,"soil_moisture_root_zone":0.119,"soil_moisture_root_zone_irri_fcdp0":0.134,"soil_moisture_root_zone_irri_fcdp1":0.133,"soil_moisture_root_zone_irri_fcdp2":0.132,"soil_moisture_root_zone_irri_fcdp3":0.132,"soil_moisture_root_zone_irri_fcdp4":0.131,"soil_moisture_root_zone_irri_fcdp5":0.13,"soil_moisture_root_zone_irri_fcdp6":0.13,"soil_moisture_root_zone_irri_fcdp7":0.139,"soil_moisture_root_zone_no_irri_fcdp0":0.119,"soil_moisture_root_zone_no_irri_fcdp1":0.118,"soil_moisture_root_zone_no_irri_fcdp2":0.117,"soil_moisture_root_zone_no_irri_fcdp3":0.117,"soil_moisture_root_zone_no_irri_fcdp4":0.116,"soil_moisture_root_zone_no_irri_fcdp5":0.116,"soil_moisture_root_zone_no_irri_fcdp6":0.115,"soil_moisture_root_zone_no_irri_fcdp7":0.114,"soil_temperature":11.197,"soil_water_potential_critical":-1000,"soil_water_potential_fc":-100,"soil_water_potential_percentile5":-1069.142,"soil_water_potential_percentile95":-734.287,"soil_water_potential_root_zone":-904.1,"solar_radiation_cumulative":176244.7,"stomatal_conductance":2.6,"sugar_content_cane":16.164,"thermal_degrees_days_cumulative":9579.186,"thermal_update":1,"theta_fc_sub":0.242,"theta_sat_sub":0.427,"theta_wp_sub":0.105,"time_until_next_irrigation":0,"uniformity_soil_moisture":0.017,"uniformity_vegetation_cover_stdmean":0.18,"utc_ls_datetime":"2025-01-12 18:40","utc_s2_datetime":"2025-01-10 18:46","vegetation_cover":31.1,"vegetation_cover_percentile5":22.6,"vegetation_cover_percentile95":39.7,"visible_update":1,"water_productivity_avg_10d":3.01,"water_unlimited_crop_production":20.7},"20303241-c281-4861-90c7-e69c32ad0e49":{"name":"Field 6 AS_Independence 22x18","date":"2025-10-04","actual_crop_production":56.1,"actual_evapotranspiration":0.9,"actual_evapotranspiration_applied_water":0.25,"actual_evapotranspiration_applied_water_cumulative":1119.6,"actual_evapotranspiration_cumulative":1983.77,"actual_transpiration":0.4,"actual_transpiration_cumulative":1183,"adviced_applied_water":12.7,"air_temperature_24":6.4,"applied_water_avg_10d":0.36,"applied_water_fcdp0":12.684,"applied_water_fcdp1":0,"applied_water_fcdp2":0,"applied_water_fcdp3":0,"applied_water_fcdp4":0,"applied_water_fcdp5":0,"applied_water_fcdp6":0,"applied_water_fcdp7":0,"area_percentage_over_irrigation":0,"area_percentage_requiring_irrigation":74,"attainable_crop_production":64.463,"critical_soil_moisture_root_zone":0.114,"crop_production_cumulative":84970,"crop_production_percentile5":42.53,"crop_production_percentile95":65.533,"et_fcdp0":0.768,"et_fcdp1":0.795,"et_fcdp2":0.848,"et_fcdp3":0.86,"et_fcdp4":0.797,"et_fcdp5":0.646,"et_fcdp6":0.722,"et_fcdp7":0.729,"field_efficiency_avg_10d":0,"forecast_et0_8days_sum":10.98,"fullness":17,"irrigation_amount_cumulative":1622.09,"irrigation_yesno":1,"leaf_nitrogen":1.469,"leaf_water_potential":-51.196,"ls_day":1,"moisture_content_cane":68.869,"net_carbon_supply_in_soil":2.6579,"ndvi":0.51,"organic_matter":1.512,"penmann_monteith_crop_coefficient_kc_avg_10d":0.39,"penmann_monteith_reference_et0":1.5,"potential_transpiration":0.4,"precipitation_avg_10d":1.61,"precipitation_cumulative":896.99,"precipitation_fcdp0":0,"precipitation_fcdp1":0,"precipitation_fcdp2":0,"precipitation_fcdp3":0,"precipitation_fcdp4":0,"precipitation_fcdp5":0,"precipitation_fcdp6":0,"precipitation_fcdp7":0,"production_gap":8.401,"quality_per":100,"relative_humidity_24":58.9,"root_depth":1050,"s2_day":0,"soil_moisture_holding_capacity":135,"soil_moisture_percentile5":0.122,"soil_moisture_percentile95":0.13,"soil_moisture_root_zone":0.126,"soil_moisture_root_zone_irri_fcdp0":0.138,"soil_moisture_root_zone_irri_fcdp1":0.138,"soil_moisture_root_zone_irri_fcdp2":0.137,"soil_moisture_root_zone_irri_fcdp3":0.136,"soil_moisture_root_zone_irri_fcdp4":0.135,"soil_moisture_root_zone_irri_fcdp5":0.134,"soil_moisture_root_zone_irri_fcdp6":0.134,"soil_moisture_root_zone_irri_fcdp7":0.133,"soil_moisture_root_zone_no_irri_fcdp0":0.125,"soil_moisture_root_zone_no_irri_fcdp1":0.124,"soil_moisture_root_zone_no_irri_fcdp2":0.124,"soil_moisture_root_zone_no_irri_fcdp3":0.123,"soil_moisture_root_zone_no_irri_fcdp4":0.122,"soil_moisture_root_zone_no_irri_fcdp5":0.121,"soil_moisture_root_zone_no_irri_fcdp6":0.121,"soil_moisture_root_zone_no_irri_fcdp7":0.12,"soil_temperature":10.912,"soil_water_potential_critical":-1000,"soil_water_potential_fc":-100,"soil_water_potential_percentile5":-619.483,"soil_water_potential_percentile95":-463.628,"soil_water_potential_root_zone":-536.3,"solar_radiation_cumulative":176244.9,"stomatal_conductance":3.96,"sugar_content_cane":14.179,"thermal_degrees_days_cumulative":9583.687,"thermal_update":1,"theta_fc_sub":0.237,"theta_sat_sub":0.425,"theta_wp_sub":0.102,"time_until_next_irrigation":0,"uniformity_soil_moisture":0.016,"uniformity_vegetation_cover_stdmean":0.087,"utc_ls_datetime":"2025-01-12 18:40","utc_s2_datetime":"2025-01-10 18:46","vegetation_cover":60.6,"vegetation_cover_percentile5":50.6,"vegetation_cover_percentile95":67.1,"visible_update":1,"water_productivity_avg_10d":9.53,"water_unlimited_crop_production":56.1},"3e35e2a8-fde1-4360-a4e1-1e4059b89486":{"name":"Field 4_22x18 NP, Carmel, Aldrich","date":"2025-10-04","actual_crop_production":33.9,"actual_evapotranspiration":0.9,"actual_evapotranspiration_applied_water":0.35,"actual_evapotranspiration_applied_water_cumulative":1397.38,"actual_evapotranspiration_cumulative":2319.77,"actual_transpiration":0.3,"actual_transpiration_cumulative":1337.3,"adviced_applied_water":10.2,"air_temperature_24":6.4,"applied_water_avg_10d":0.27,"applied_water_fcdp0":10.236,"applied_water_fcdp1":0,"applied_water_fcdp2":0,"applied_water_fcdp3":0,"applied_water_fcdp4":0,"applied_water_fcdp5":0,"applied_water_fcdp6":0,"applied_water_fcdp7":0,"area_percentage_over_irrigation":0,"area_percentage_requiring_irrigation":98,"attainable_crop_production":41.637,"critical_soil_moisture_root_zone":0.124,"crop_production_cumulative":89799,"crop_production_percentile5":27.38,"crop_production_percentile95":44.659,"et_fcdp0":0.85,"et_fcdp1":0.874,"et_fcdp2":0.934,"et_fcdp3":0.948,"et_fcdp4":0.878,"et_fcdp5":0.707,"et_fcdp6":0.796,"et_fcdp7":0.803,"field_efficiency_avg_10d":0,"forecast_et0_8days_sum":10.55,"fullness":16,"irrigation_amount_cumulative":1962.44,"irrigation_yesno":1,"leaf_nitrogen":1.225,"leaf_water_potential":-53.335,"ls_day":1,"moisture_content_cane":67.501,"net_carbon_supply_in_soil":1.6774,"ndvi":0.4,"organic_matter":2.669,"penmann_monteith_crop_coefficient_kc_avg_10d":0.46,"penmann_monteith_reference_et0":1.5,"potential_transpiration":0.3,"precipitation_avg_10d":1.61,"precipitation_cumulative":896.99,"precipitation_fcdp0":0,"precipitation_fcdp1":0,"precipitation_fcdp2":0,"precipitation_fcdp3":0,"precipitation_fcdp4":0,"precipitation_fcdp5":0,"precipitation_fcdp6":0,"precipitation_fcdp7":0,"production_gap":7.784,"quality_per":100,"relative_humidity_24":58.9,"root_depth":1063,"s2_day":0,"soil_moisture_holding_capacity":141,"soil_moisture_percentile5":0.129,"soil_moisture_percentile95":0.135,"soil_moisture_root_zone":0.132,"soil_moisture_root_zone_irri_fcdp0":0.144,"soil_moisture_root_zone_irri_fcdp1":0.143,"soil_moisture_root_zone_irri_fcdp2":0.142,"soil_moisture_root_zone_irri_fcdp3":0.141,"soil_moisture_root_zone_irri_fcdp4":0.141,"soil_moisture_root_zone_irri_fcdp5":0.14,"soil_moisture_root_zone_irri_fcdp6":0.139,"soil_moisture_root_zone_irri_fcdp7":0.138,"soil_moisture_root_zone_no_irri_fcdp0":0.131,"soil_moisture_root_zone_no_irri_fcdp1":0.13,"soil_moisture_root_zone_no_irri_fcdp2":0.129,"soil_moisture_root_zone_no_irri_fcdp3":0.128,"soil_moisture_root_zone_no_irri_fcdp4":0.128,"soil_moisture_root_zone_no_irri_fcdp5":0.127,"soil_moisture_root_zone_no_irri_fcdp6":0.126,"soil_moisture_root_zone_no_irri_fcdp7":0.125,"soil_temperature":10.77,"soil_water_potential_critical":-1000,"soil_water_potential_fc":-100,"soil_water_potential_percentile5":-732.364,"soil_water_potential_percentile95":-569.818,"soil_water_potential_root_zone":-651.4,"solar_radiation_cumulative":176237.9,"stomatal_conductance":3.62,"sugar_content_cane":15.275,"thermal_degrees_days_cumulative":9583.688,"thermal_update":1,"theta_fc_sub":0.25,"theta_sat_sub":0.431,"theta_wp_sub":0.109,"time_until_next_irrigation":0,"uniformity_soil_moisture":0.015,"uniformity_vegetation_cover_stdmean":0.102,"utc_ls_datetime":"2025-01-12 18:40","utc_s2_datetime":"2025-01-10 18:46","vegetation_cover":43.1,"vegetation_cover_percentile5":38,"vegetation_cover_percentile95":51.8,"visible_update":1,"water_productivity_avg_10d":4.87,"water_unlimited_crop_production":33.9},"1d6c339a-7d6a-48ef-875a-947f64b35ee9":{"name":"Field 6 AN_Independence 22x18","date":"2025-10-04","actual_crop_production":37.2,"actual_evapotranspiration":0.9,"actual_evapotranspiration_applied_water":0.26,"actual_evapotranspiration_applied_water_cumulative":1044.89,"actual_evapotranspiration_cumulative":1805.42,"actual_transpiration":0.3,"actual_transpiration_cumulative":948.3,"adviced_applied_water":10.6,"air_temperature_24":6.4,"applied_water_avg_10d":0.21,"applied_water_fcdp0":10.64,"applied_water_fcdp1":0,"applied_water_fcdp2":0,"applied_water_fcdp3":0,"applied_water_fcdp4":0,"applied_water_fcdp5":0,"applied_water_fcdp6":0,"applied_water_fcdp7":0,"area_percentage_over_irrigation":0,"area_percentage_requiring_irrigation":100,"attainable_crop_production":37.241,"critical_soil_moisture_root_zone":0.119,"crop_production_cumulative":58233,"crop_production_percentile5":37.241,"crop_production_percentile95":37.241,"et_fcdp0":0.792,"et_fcdp1":0.814,"et_fcdp2":0.869,"et_fcdp3":0.883,"et_fcdp4":0.817,"et_fcdp5":0.656,"et_fcdp6":0.741,"et_fcdp7":0.749,"field_efficiency_avg_10d":0,"forecast_et0_8days_sum":10.37,"fullness":15,"irrigation_amount_cumulative":1520.31,"irrigation_yesno":1,"leaf_nitrogen":1.112,"leaf_water_potential":-51.65,"ls_day":1,"moisture_content_cane":67.126,"net_carbon_supply_in_soil":2.0157,"ndvi":0.42,"organic_matter":1.831,"penmann_monteith_crop_coefficient_kc_avg_10d":0.43,"penmann_monteith_reference_et0":1.5,"potential_transpiration":0.3,"precipitation_avg_10d":1.61,"precipitation_cumulative":896.99,"precipitation_fcdp0":0,"precipitation_fcdp1":0,"precipitation_fcdp2":0,"precipitation_fcdp3":0,"precipitation_fcdp4":0,"precipitation_fcdp5":0,"precipitation_fcdp6":0,"precipitation_fcdp7":0,"production_gap":0,"quality_per":100,"relative_humidity_24":58.9,"root_depth":977,"s2_day":0,"soil_moisture_holding_capacity":137,"soil_moisture_percentile5":0.127,"soil_moisture_percentile95":0.127,"soil_moisture_root_zone":0.127,"soil_moisture_root_zone_irri_fcdp0":0.14,"soil_moisture_root_zone_irri_fcdp1":0.14,"soil_moisture_root_zone_irri_fcdp2":0.139,"soil_moisture_root_zone_irri_fcdp3":0.138,"soil_moisture_root_zone_irri_fcdp4":0.137,"soil_moisture_root_zone_irri_fcdp5":0.136,"soil_moisture_root_zone_irri_fcdp6":0.135,"soil_moisture_root_zone_irri_fcdp7":0.135,"soil_moisture_root_zone_no_irri_fcdp0":0.126,"soil_moisture_root_zone_no_irri_fcdp1":0.126,"soil_moisture_root_zone_no_irri_fcdp2":0.125,"soil_moisture_root_zone_no_irri_fcdp3":0.124,"soil_moisture_root_zone_no_irri_fcdp4":0.123,"soil_moisture_root_zone_no_irri_fcdp5":0.122,"soil_moisture_root_zone_no_irri_fcdp6":0.121,"soil_moisture_root_zone_no_irri_fcdp7":0.121,"soil_temperature":11.058,"soil_water_potential_critical":-1000,"soil_water_potential_fc":-100,"soil_water_potential_percentile5":-627.482,"soil_water_potential_percentile95":-627.482,"soil_water_potential_root_zone":-627.5,"solar_radiation_cumulative":176238.2,"stomatal_conductance":3.71,"sugar_content_cane":15.577,"thermal_degrees_days_cumulative":9583.686,"thermal_update":1,"theta_fc_sub":0.243,"theta_sat_sub":0.428,"theta_wp_sub":0.106,"time_until_next_irrigation":0,"uniformity_soil_moisture":0,"uniformity_vegetation_cover_stdmean":0,"utc_ls_datetime":"2025-01-12 18:40","utc_s2_datetime":"2025-01-10 18:46","vegetation_cover":46,"vegetation_cover_percentile5":46,"vegetation_cover_percentile95":46,"visible_update":1,"water_productivity_avg_10d":5.35,"water_unlimited_crop_production":37.2},"278562c1-4c05-4c92-8c95-53fdb9541b54":{"name":"Field 2_22x18 Butte and padre","date":"2025-10-04","actual_crop_production":36,"actual_evapotranspiration":0.8,"actual_evapotranspiration_applied_water":0.27,"actual_evapotranspiration_applied_water_cumulative":1357.5,"actual_evapotranspiration_cumulative":2217.62,"actual_transpiration":0.3,"actual_transpiration_cumulative":1395.3,"adviced_applied_water":10.6,"air_temperature_24":6.4,"applied_water_avg_10d":0.2,"applied_water_fcdp0":10.558,"applied_water_fcdp1":0,"applied_water_fcdp2":0,"applied_water_fcdp3":0,"applied_water_fcdp4":0,"applied_water_fcdp5":0,"applied_water_fcdp6":0,"applied_water_fcdp7":0,"area_percentage_over_irrigation":0,"area_percentage_requiring_irrigation":100,"attainable_crop_production":42.199,"critical_soil_moisture_root_zone":0.116,"crop_production_cumulative":93775,"crop_production_percentile5":27.579,"crop_production_percentile95":43.668,"et_fcdp0":0.752,"et_fcdp1":0.774,"et_fcdp2":0.827,"et_fcdp3":0.839,"et_fcdp4":0.777,"et_fcdp5":0.625,"et_fcdp6":0.705,"et_fcdp7":0.709,"field_efficiency_avg_10d":0,"forecast_et0_8days_sum":10.54,"fullness":14,"irrigation_amount_cumulative":1921.6,"irrigation_yesno":1,"leaf_nitrogen":1.2,"leaf_water_potential":-50.643,"ls_day":1,"moisture_content_cane":67.294,"net_carbon_supply_in_soil":1.9942,"ndvi":0.41,"organic_matter":1.77,"penmann_monteith_crop_coefficient_kc_avg_10d":0.39,"penmann_monteith_reference_et0":1.5,"potential_transpiration":0.3,"precipitation_avg_10d":1.61,"precipitation_cumulative":896.99,"precipitation_fcdp0":0,"precipitation_fcdp1":0,"precipitation_fcdp2":0,"precipitation_fcdp3":0,"precipitation_fcdp4":0,"precipitation_fcdp5":0,"precipitation_fcdp6":0,"precipitation_fcdp7":0,"production_gap":6.214,"quality_per":100,"relative_humidity_24":58.9,"root_depth":1069,"s2_day":0,"soil_moisture_holding_capacity":136,"soil_moisture_percentile5":0.119,"soil_moisture_percentile95":0.126,"soil_moisture_root_zone":0.123,"soil_moisture_root_zone_irri_fcdp0":0.135,"soil_moisture_root_zone_irri_fcdp1":0.135,"soil_moisture_root_zone_irri_fcdp2":0.134,"soil_moisture_root_zone_irri_fcdp3":0.133,"soil_moisture_root_zone_irri_fcdp4":0.132,"soil_moisture_root_zone_irri_fcdp5":0.132,"soil_moisture_root_zone_irri_fcdp6":0.131,"soil_moisture_root_zone_irri_fcdp7":0.13,"soil_moisture_root_zone_no_irri_fcdp0":0.123,"soil_moisture_root_zone_no_irri_fcdp1":0.122,"soil_moisture_root_zone_no_irri_fcdp2":0.121,"soil_moisture_root_zone_no_irri_fcdp3":0.12,"soil_moisture_root_zone_no_irri_fcdp4":0.12,"soil_moisture_root_zone_no_irri_fcdp5":0.119,"soil_moisture_root_zone_no_irri_fcdp6":0.118,"soil_moisture_root_zone_no_irri_fcdp7":0.118,"soil_temperature":11.265,"soil_water_potential_critical":-1000,"soil_water_potential_fc":-100,"soil_water_potential_percentile5":-822.159,"soil_water_potential_percentile95":-578.228,"soil_water_potential_root_zone":-671.3,"solar_radiation_cumulative":176238,"stomatal_conductance":3.54,"sugar_content_cane":15.442,"thermal_degrees_days_cumulative":9579.188,"thermal_update":1,"theta_fc_sub":0.24,"theta_sat_sub":0.426,"theta_wp_sub":0.104,"time_until_next_irrigation":0,"uniformity_soil_moisture":0.016,"uniformity_vegetation_cover_stdmean":0.084,"utc_ls_datetime":"2025-01-12 18:40","utc_s2_datetime":"2025-01-10 18:46","vegetation_cover":45.4,"vegetation_cover_percentile5":39.2,"vegetation_cover_percentile95":51.9,"visible_update":1,"water_productivity_avg_10d":6.14,"water_unlimited_crop_production":36},"c49f3199-1a88-4895-ae82-460204d31d73":{"name":"Field 6 A_Independence 22x9","date":"2025-10-04","actual_crop_production":43.5,"actual_evapotranspiration":0.9,"actual_evapotranspiration_applied_water":0.27,"actual_evapotranspiration_applied_water_cumulative":1099.07,"actual_evapotranspiration_cumulative":1824.95,"actual_transpiration":0.4,"actual_transpiration_cumulative":958.7,"adviced_applied_water":11.4,"air_temperature_24":6.4,"applied_water_avg_10d":0.28,"applied_water_fcdp0":11.415,"applied_water_fcdp1":0,"applied_water_fcdp2":0,"applied_water_fcdp3":0,"applied_water_fcdp4":0,"applied_water_fcdp5":0,"applied_water_fcdp6":0,"applied_water_fcdp7":0,"area_percentage_over_irrigation":0,"area_percentage_requiring_irrigation":100,"attainable_crop_production":48.447,"critical_soil_moisture_root_zone":0.121,"crop_production_cumulative":54495,"crop_production_percentile5":28.933,"crop_production_percentile95":49.108,"et_fcdp0":0.781,"et_fcdp1":0.81,"et_fcdp2":0.864,"et_fcdp3":0.876,"et_fcdp4":0.812,"et_fcdp5":0.66,"et_fcdp6":0.736,"et_fcdp7":0.741,"field_efficiency_avg_10d":0,"forecast_et0_8days_sum":11.09,"fullness":16,"irrigation_amount_cumulative":1549.52,"irrigation_yesno":1,"leaf_nitrogen":1.355,"leaf_water_potential":-53.174,"ls_day":1,"moisture_content_cane":68.013,"net_carbon_supply_in_soil":2.2168,"ndvi":0.45,"organic_matter":1.817,"penmann_monteith_crop_coefficient_kc_avg_10d":0.4,"penmann_monteith_reference_et0":1.5,"potential_transpiration":0.4,"precipitation_avg_10d":1.61,"precipitation_cumulative":896.99,"precipitation_fcdp0":0,"precipitation_fcdp1":0,"precipitation_fcdp2":0,"precipitation_fcdp3":0,"precipitation_fcdp4":0,"precipitation_fcdp5":0,"precipitation_fcdp6":0,"precipitation_fcdp7":0,"production_gap":4.984,"quality_per":100,"relative_humidity_24":58.9,"root_depth":958,"s2_day":0,"soil_moisture_holding_capacity":139,"soil_moisture_percentile5":0.126,"soil_moisture_percentile95":0.133,"soil_moisture_root_zone":0.13,"soil_moisture_root_zone_irri_fcdp0":0.144,"soil_moisture_root_zone_irri_fcdp1":0.143,"soil_moisture_root_zone_irri_fcdp2":0.142,"soil_moisture_root_zone_irri_fcdp3":0.141,"soil_moisture_root_zone_irri_fcdp4":0.14,"soil_moisture_root_zone_irri_fcdp5":0.139,"soil_moisture_root_zone_irri_fcdp6":0.139,"soil_moisture_root_zone_irri_fcdp7":0.138,"soil_moisture_root_zone_no_irri_fcdp0":0.129,"soil_moisture_root_zone_no_irri_fcdp1":0.129,"soil_moisture_root_zone_no_irri_fcdp2":0.128,"soil_moisture_root_zone_no_irri_fcdp3":0.127,"soil_moisture_root_zone_no_irri_fcdp4":0.126,"soil_moisture_root_zone_no_irri_fcdp5":0.125,"soil_moisture_root_zone_no_irri_fcdp6":0.124,"soil_moisture_root_zone_no_irri_fcdp7":0.124,"soil_temperature":10.898,"soil_water_potential_critical":-1000,"soil_water_potential_fc":-100,"soil_water_potential_percentile5":-756.988,"soil_water_potential_percentile95":-545.142,"soil_water_potential_root_zone":-620.5,"solar_radiation_cumulative":176257.4,"stomatal_conductance":3.65,"sugar_content_cane":14.865,"thermal_degrees_days_cumulative":9579.187,"thermal_update":1,"theta_fc_sub":0.246,"theta_sat_sub":0.429,"theta_wp_sub":0.107,"time_until_next_irrigation":0,"uniformity_soil_moisture":0.015,"uniformity_vegetation_cover_stdmean":0.087,"utc_ls_datetime":"2025-01-12 18:40","utc_s2_datetime":"2025-01-10 18:46","vegetation_cover":51.5,"vegetation_cover_percentile5":41,"vegetation_cover_percentile95":55.5,"visible_update":1,"water_productivity_avg_10d":6.37,"water_unlimited_crop_production":43.5},"3a5c029c-75a9-4962-8921-aa1794b9e9e4":{"name":"Field 5_22x18 Non pareil, carmel, aldrich.","date":"2025-10-04","actual_crop_production":23.4,"actual_evapotranspiration":0.4,"actual_evapotranspiration_applied_water":0.08,"actual_evapotranspiration_applied_water_cumulative":392.84,"actual_evapotranspiration_cumulative":813.54,"actual_transpiration":0.1,"actual_transpiration_cumulative":346.5,"adviced_applied_water":9.2,"air_temperature_24":6.4,"applied_water_avg_10d":0.08,"applied_water_fcdp0":9.25,"applied_water_fcdp1":0,"applied_water_fcdp2":0,"applied_water_fcdp3":0,"applied_water_fcdp4":0,"applied_water_fcdp5":0,"applied_water_fcdp6":0,"applied_water_fcdp7":0,"area_percentage_over_irrigation":0,"area_percentage_requiring_irrigation":100,"attainable_crop_production":27.928,"critical_soil_moisture_root_zone":0.114,"crop_production_cumulative":13805,"crop_production_percentile5":16.479,"crop_production_percentile95":29.343,"et_fcdp0":0.454,"et_fcdp1":0.468,"et_fcdp2":0.5,"et_fcdp3":0.507,"et_fcdp4":0.47,"et_fcdp5":0.379,"et_fcdp6":0.426,"et_fcdp7":0.401,"field_efficiency_avg_10d":0,"forecast_et0_8days_sum":10.72,"fullness":9,"irrigation_amount_cumulative":598.54,"irrigation_yesno":1,"leaf_nitrogen":1.073,"leaf_water_potential":-28.47,"ls_day":1,"moisture_content_cane":66.458,"net_carbon_supply_in_soil":1.7521,"ndvi":0.35,"organic_matter":1.782,"penmann_monteith_crop_coefficient_kc_avg_10d":0.27,"penmann_monteith_reference_et0":1.5,"potential_transpiration":0.1,"precipitation_avg_10d":1.61,"precipitation_cumulative":896.99,"precipitation_fcdp0":0,"precipitation_fcdp1":0,"precipitation_fcdp2":0,"precipitation_fcdp3":0,"precipitation_fcdp4":0,"precipitation_fcdp5":0,"precipitation_fcdp6":0,"precipitation_fcdp7":0,"production_gap":4.568,"quality_per":100,"relative_humidity_24":58.9,"root_depth":758,"s2_day":0,"soil_moisture_holding_capacity":135,"soil_moisture_percentile5":0.115,"soil_moisture_percentile95":0.117,"soil_moisture_root_zone":0.116,"soil_moisture_root_zone_irri_fcdp0":0.134,"soil_moisture_root_zone_irri_fcdp1":0.133,"soil_moisture_root_zone_irri_fcdp2":0.132,"soil_moisture_root_zone_irri_fcdp3":0.132,"soil_moisture_root_zone_irri_fcdp4":0.131,"soil_moisture_root_zone_irri_fcdp5":0.13,"soil_moisture_root_zone_irri_fcdp6":0.13,"soil_moisture_root_zone_irri_fcdp7":0.129,"soil_moisture_root_zone_no_irri_fcdp0":0.116,"soil_moisture_root_zone_no_irri_fcdp1":0.115,"soil_moisture_root_zone_no_irri_fcdp2":0.114,"soil_moisture_root_zone_no_irri_fcdp3":0.114,"soil_moisture_root_zone_no_irri_fcdp4":0.113,"soil_moisture_root_zone_no_irri_fcdp5":0.112,"soil_moisture_root_zone_no_irri_fcdp6":0.112,"soil_moisture_root_zone_no_irri_fcdp7":0.111,"soil_temperature":11.52,"soil_water_potential_critical":-1000,"soil_water_potential_fc":-100,"soil_water_potential_percentile5":-906.92,"soil_water_potential_percentile95":-812.358,"soil_water_potential_root_zone":-858.5,"solar_radiation_cumulative":176235.9,"stomatal_conductance":2.67,"sugar_content_cane":16.112,"thermal_degrees_days_cumulative":9579.187,"thermal_update":1,"theta_fc_sub":0.237,"theta_sat_sub":0.425,"theta_wp_sub":0.102,"time_until_next_irrigation":0,"uniformity_soil_moisture":0.009,"uniformity_vegetation_cover_stdmean":0.094,"utc_ls_datetime":"2025-01-12 18:40","utc_s2_datetime":"2025-01-10 18:46","vegetation_cover":36.1,"vegetation_cover_percentile5":30.2,"vegetation_cover_percentile95":41.6,"visible_update":1,"water_productivity_avg_10d":4.45,"water_unlimited_crop_production":24.3},"32120f7a-8441-458a-9275-8c94fdad2faf":{"name":"Field 3S_22x18 Butte and padre","date":"2025-10-04","actual_crop_production":36.4,"actual_evapotranspiration":0.8,"actual_evapotranspiration_applied_water":0.33,"actual_evapotranspiration_applied_water_cumulative":1343.92,"actual_evapotranspiration_cumulative":2146.03,"actual_transpiration":0.3,"actual_transpiration_cumulative":1295.3,"adviced_applied_water":10.6,"air_temperature_24":6.4,"applied_water_avg_10d":0.41,"applied_water_fcdp0":10.634,"applied_water_fcdp1":0,"applied_water_fcdp2":0,"applied_water_fcdp3":0,"applied_water_fcdp4":0,"applied_water_fcdp5":0,"applied_water_fcdp6":0,"applied_water_fcdp7":3.986,"area_percentage_over_irrigation":0,"area_percentage_requiring_irrigation":97,"attainable_crop_production":44.175,"critical_soil_moisture_root_zone":0.128,"crop_production_cumulative":90504,"crop_production_percentile5":22.679,"crop_production_percentile95":45.529,"et_fcdp0":0.765,"et_fcdp1":0.79,"et_fcdp2":0.844,"et_fcdp3":0.856,"et_fcdp4":0.793,"et_fcdp5":0.641,"et_fcdp6":0.719,"et_fcdp7":0.722,"field_efficiency_avg_10d":0,"forecast_et0_8days_sum":10.81,"fullness":16,"irrigation_amount_cumulative":1903.2,"irrigation_yesno":1,"leaf_nitrogen":1.226,"leaf_water_potential":-40.911,"ls_day":1,"moisture_content_cane":67.326,"net_carbon_supply_in_soil":1.7184,"ndvi":0.42,"organic_matter":2.806,"penmann_monteith_crop_coefficient_kc_avg_10d":0.4,"penmann_monteith_reference_et0":1.5,"potential_transpiration":0.3,"precipitation_avg_10d":1.61,"precipitation_cumulative":896.99,"precipitation_fcdp0":0,"precipitation_fcdp1":0,"precipitation_fcdp2":0,"precipitation_fcdp3":0,"precipitation_fcdp4":0,"precipitation_fcdp5":0,"precipitation_fcdp6":0,"precipitation_fcdp7":0,"production_gap":7.8,"quality_per":100,"relative_humidity_24":58.9,"root_depth":1064,"s2_day":0,"soil_moisture_holding_capacity":142,"soil_moisture_percentile5":0.13,"soil_moisture_percentile95":0.14,"soil_moisture_root_zone":0.135,"soil_moisture_root_zone_irri_fcdp0":0.147,"soil_moisture_root_zone_irri_fcdp1":0.146,"soil_moisture_root_zone_irri_fcdp2":0.145,"soil_moisture_root_zone_irri_fcdp3":0.145,"soil_moisture_root_zone_irri_fcdp4":0.144,"soil_moisture_root_zone_irri_fcdp5":0.143,"soil_moisture_root_zone_irri_fcdp6":0.142,"soil_moisture_root_zone_irri_fcdp7":0.147,"soil_moisture_root_zone_no_irri_fcdp0":0.134,"soil_moisture_root_zone_no_irri_fcdp1":0.133,"soil_moisture_root_zone_no_irri_fcdp2":0.132,"soil_moisture_root_zone_no_irri_fcdp3":0.132,"soil_moisture_root_zone_no_irri_fcdp4":0.131,"soil_moisture_root_zone_no_irri_fcdp5":0.13,"soil_moisture_root_zone_no_irri_fcdp6":0.13,"soil_moisture_root_zone_no_irri_fcdp7":0.129,"soil_temperature":11.217,"soil_water_potential_critical":-1000,"soil_water_potential_fc":-100,"soil_water_potential_percentile5":-884.916,"soil_water_potential_percentile95":-551.248,"soil_water_potential_root_zone":-695.6,"solar_radiation_cumulative":176245.6,"stomatal_conductance":3.46,"sugar_content_cane":15.416,"thermal_degrees_days_cumulative":9583.687,"thermal_update":1,"theta_fc_sub":0.254,"theta_sat_sub":0.433,"theta_wp_sub":0.112,"time_until_next_irrigation":0,"uniformity_soil_moisture":0.022,"uniformity_vegetation_cover_stdmean":0.113,"utc_ls_datetime":"2025-01-12 18:40","utc_s2_datetime":"2025-01-10 18:46","vegetation_cover":46,"vegetation_cover_percentile5":34.2,"vegetation_cover_percentile95":52.8,"visible_update":1,"water_productivity_avg_10d":6.25,"water_unlimited_crop_production":36.4}}